{"000660.KS":{"2016-03":{"매출액_QoQ":null,"매출액_YoY":null,"매출총이익률":36.1,"매출총이익률_QoQ":null,"매출총이익률_YoY":null,"영업이익률":15.4,"영업이익률_QoQ":null,"영업이익률_YoY":null,"periodEndMonth":"2016-03"},"2016-06":{"매출액_QoQ":7.8,"매출액_YoY":null,"매출총이익률":31.8,"매출총이익률_QoQ":-4.3,"매출총이익률_YoY":null,"영업이익률":11.5,"영업이익률_QoQ":-3.9,"영업이익률_YoY":null,"periodEndMonth":"2016-06"},"2016-09":{"매출액_QoQ":7.7,"매출액_YoY":null,"매출총이익률":34.2,"매출총이익률_QoQ":2.4,"매출총이익률_YoY":null,"영업이익률":17.1,"영업이익률_QoQ":5.6,"영업이익률_YoY":null,"periodEndMonth":"2016-09"},"2016-12":{"매출액_QoQ":26.2,"매출액_YoY":null,"매출총이익률":44.6,"매출총이익률_QoQ":10.4,"매출총이익률_YoY":null,"영업이익률":28.7,"영업이익률_QoQ":11.6,"영업이익률_YoY":null,"periodEndMonth":"2016-12"},"2017-03":{"매출액_QoQ":17.4,"매출액_YoY":72,"매출총이익률":52.5,"매출총이익률_QoQ":7.9,"매출총이익률_YoY":16.4,"영업이익률":39.2,"영업이익률_QoQ":10.5,"영업이익률_YoY":23.8,"periodEndMonth":"2017-03"},"2017-06":{"매출액_QoQ":6.4,"매출액_YoY":69.8,"매출총이익률":57.3,"매출총이익률_QoQ":4.8,"매출총이익률_YoY":25.5,"영업이익률":45.6,"영업이익률_QoQ":6.4,"영업이익률_YoY":34.1,"periodEndMonth":"2017-06"},"2017-09":{"매출액_QoQ":21,"매출액_YoY":90.9,"매출총이익률":58,"매출총이익률_QoQ":0.7,"매출총이익률_YoY":23.8,"영업이익률":46.1,"영업이익률_QoQ":0.5,"영업이익률_YoY":29,"periodEndMonth":"2017-09"},"2017-12":{"매출액_QoQ":11.5,"매출액_YoY":68.5,"매출총이익률":61.7,"매출총이익률_QoQ":3.7,"매출총이익률_YoY":17.1,"영업이익률":49.5,"영업이익률_QoQ":3.4,"영업이익률_YoY":20.8,"periodEndMonth":"2017-12"},"2018-03":{"매출액_QoQ":-3.4,"매출액_YoY":38.6,"매출총이익률":61.2,"매출총이익률_QoQ":-0.5,"매출총이익률_YoY":8.7,"영업이익률":50.1,"영업이익률_QoQ":0.6,"영업이익률_YoY":10.9,"periodEndMonth":"2018-03"},"2018-06":{"매출액_QoQ":18.9,"매출액_YoY":55,"매출총이익률":63.7,"매출총이익률_QoQ":2.5,"매출총이익률_YoY":6.4,"영업이익률":53.7,"영업이익률_QoQ":3.6,"영업이익률_YoY":8.1,"periodEndMonth":"2018-06"},"2018-09":{"매출액_QoQ":10.1,"매출액_YoY":41,"매출총이익률":66.1,"매출총이익률_QoQ":2.4,"매출총이익률_YoY":8.1,"영업이익률":56.7,"영업이익률_QoQ":3,"영업이익률_YoY":10.6,"periodEndMonth":"2018-09"},"2018-12":{"매출액_QoQ":-13,"매출액_YoY":10.1,"매출총이익률":58.1,"매출총이익률_QoQ":-8,"매출총이익률_YoY":-3.6,"영업이익률":44.6,"영업이익률_QoQ":-12.1,"영업이익률_YoY":-4.9,"periodEndMonth":"2018-12"},"2019-03":{"매출액_QoQ":-31.8,"매출액_YoY":-22.3,"매출총이익률":39.6,"매출총이익률_QoQ":-18.5,"매출총이익률_YoY":-21.6,"영업이익률":20.2,"영업이익률_QoQ":-24.4,"영업이익률_YoY":-29.9,"periodEndMonth":"2019-03"},"2019-06":{"매출액_QoQ":-4.7,"매출액_YoY":-37.8,"매출총이익률":31.3,"매출총이익률_QoQ":-8.3,"매출총이익률_YoY":-32.4,"영업이익률":9.9,"영업이익률_QoQ":-10.3,"영업이익률_YoY":-43.8,"periodEndMonth":"2019-06"},"2019-09":{"매출액_QoQ":6,"매출액_YoY":-40.1,"매출총이익률":26.6,"매출총이익률_QoQ":-4.7,"매출총이익률_YoY":-39.5,"영업이익률":6.9,"영업이익률_QoQ":-3,"영업이익률_YoY":-49.8,"periodEndMonth":"2019-09"},"2019-12":{"매출액_QoQ":1.3,"매출액_YoY":-30.3,"매출총이익률":23.9,"매출총이익률_QoQ":-2.7,"매출총이익률_YoY":-34.2,"영업이익률":3.4,"영업이익률_QoQ":-3.5,"영업이익률_YoY":-41.2,"periodEndMonth":"2019-12"},"2020-03":{"매출액_QoQ":3.9,"매출액_YoY":6.3,"매출총이익률":30.4,"매출총이익률_QoQ":6.5,"매출총이익률_YoY":-9.2,"영업이익률":11.1,"영업이익률_QoQ":7.7,"영업이익률_YoY":-9.1,"periodEndMonth":"2020-03"},"2020-06":{"매출액_QoQ":19.6,"매출액_YoY":33.4,"매출총이익률":38.9,"매출총이익률_QoQ":8.5,"매출총이익률_YoY":7.6,"영업이익률":22.6,"영업이익률_QoQ":11.5,"영업이익률_YoY":12.7,"periodEndMonth":"2020-06"},"2020-09":{"매출액_QoQ":-5.6,"매출액_YoY":18.9,"매출총이익률":35,"매출총이익률_QoQ":-3.9,"매출총이익률_YoY":8.4,"영업이익률":16,"영업이익률_QoQ":-6.6,"영업이익률_YoY":9.1,"periodEndMonth":"2020-09"},"2020-12":{"매출액_QoQ":-2,"매출액_YoY":15,"매출총이익률":30.5,"매출총이익률_QoQ":-4.5,"매출총이익률_YoY":6.6,"영업이익률":12.1,"영업이익률_QoQ":-3.9,"영업이익률_YoY":8.7,"periodEndMonth":"2020-12"},"2021-03":{"매출액_QoQ":6.6,"매출액_YoY":18,"매출총이익률":32.1,"매출총이익률_QoQ":1.6,"매출총이익률_YoY":1.7,"영업이익률":15.6,"영업이익률_QoQ":3.5,"영업이익률_YoY":4.5,"periodEndMonth":"2021-03"},"2021-06":{"매출액_QoQ":21.5,"매출액_YoY":19.9,"매출총이익률":42,"매출총이익률_QoQ":9.9,"매출총이익률_YoY":3.1,"영업이익률":26.1,"영업이익률_QoQ":10.5,"영업이익률_YoY":3.5,"periodEndMonth":"2021-06"},"2021-09":{"매출액_QoQ":14.4,"매출액_YoY":45.2,"매출총이익률":49.4,"매출총이익률_QoQ":7.4,"매출총이익률_YoY":14.4,"영업이익률":35.3,"영업이익률_QoQ":9.2,"영업이익률_YoY":19.3,"periodEndMonth":"2021-09"},"2021-12":{"매출액_QoQ":4.8,"매출액_YoY":55.4,"매출총이익률":48.9,"매출총이익률_QoQ":-0.5,"매출총이익률_YoY":18.4,"영업이익률":34.1,"영업이익률_QoQ":-1.2,"영업이익률_YoY":22,"periodEndMonth":"2021-12"},"2022-03":{"매출액_QoQ":-1.8,"매출액_YoY":43.1,"매출총이익률":44.5,"매출총이익률_QoQ":-4.4,"매출총이익률_YoY":12.4,"영업이익률":23.5,"영업이익률_QoQ":-10.6,"영업이익률_YoY":7.9,"periodEndMonth":"2022-03"},"2022-06":{"매출액_QoQ":13.6,"매출액_YoY":33.8,"매출총이익률":45.9,"매출총이익률_QoQ":1.4,"매출총이익률_YoY":3.9,"영업이익률":30.4,"영업이익률_QoQ":6.9,"영업이익률_YoY":4.3,"periodEndMonth":"2022-06"},"2022-09":{"매출액_QoQ":-20.5,"매출액_YoY":-7,"매출총이익률":35.3,"매출총이익률_QoQ":-10.6,"매출총이익률_YoY":-14.1,"영업이익률":15.1,"영업이익률_QoQ":-15.3,"영업이익률_YoY":-20.2,"periodEndMonth":"2022-09"},"2022-12":{"매출액_QoQ":-30.1,"매출액_YoY":-38,"매출총이익률":0,"매출총이익률_QoQ":-35.3,"매출총이익률_YoY":-48.9,"영업이익률":-24.7,"영업이익률_QoQ":-39.8,"영업이익률_YoY":-58.8,"periodEndMonth":"2022-12"},"2023-03":{"매출액_QoQ":-33.7,"매출액_YoY":-58.1,"매출총이익률":-32.3,"매출총이익률_QoQ":-32.3,"매출총이익률_YoY":-76.8,"영업이익률":-66.9,"영업이익률_QoQ":-42.2,"영업이익률_YoY":-90.4,"periodEndMonth":"2023-03"},"2023-06":{"매출액_QoQ":43.6,"매출액_YoY":-47.1,"매출총이익률":-16.1,"매출총이익률_QoQ":16.2,"매출총이익률_YoY":-62,"영업이익률":-39.4,"영업이익률_QoQ":27.5,"영업이익률_YoY":-69.8,"periodEndMonth":"2023-06"},"2023-09":{"매출액_QoQ":24.1,"매출액_YoY":-17.5,"매출총이익률":0.7,"매출총이익률_QoQ":16.8,"매출총이익률_YoY":-34.6,"영업이익률":-19.8,"영업이익률_QoQ":19.6,"영업이익률_YoY":-34.9,"periodEndMonth":"2023-09"},"2023-12":{"매출액_QoQ":24.7,"매출액_YoY":47.4,"매출총이익률":19.7,"매출총이익률_QoQ":19,"매출총이익률_YoY":19.7,"영업이익률":3.1,"영업이익률_QoQ":22.9,"영업이익률_YoY":27.8,"periodEndMonth":"2023-12"},"2024-03":{"매출액_QoQ":9.9,"매출액_YoY":144.3,"매출총이익률":38.6,"매출총이익률_QoQ":18.9,"매출총이익률_YoY":70.9,"영업이익률":23.2,"영업이익률_QoQ":20.1,"영업이익률_YoY":90.1,"periodEndMonth":"2024-03"},"2024-06":{"매출액_QoQ":32.1,"매출액_YoY":124.8,"매출총이익률":45.6,"매출총이익률_QoQ":7,"매출총이익률_YoY":61.7,"영업이익률":33.3,"영업이익률_QoQ":10.1,"영업이익률_YoY":72.7,"periodEndMonth":"2024-06"},"2024-09":{"매출액_QoQ":7,"매출액_YoY":93.8,"매출총이익률":52.2,"매출총이익률_QoQ":6.6,"매출총이익률_YoY":51.5,"영업이익률":40,"영업이익률_QoQ":6.7,"영업이익률_YoY":59.8,"periodEndMonth":"2024-09"},"2024-12":{"매출액_QoQ":12.5,"매출액_YoY":74.8,"매출총이익률":52.4,"매출총이익률_QoQ":0.2,"매출총이익률_YoY":32.7,"영업이익률":40.9,"영업이익률_QoQ":0.9,"영업이익률_YoY":37.8,"periodEndMonth":"2024-12"},"2025-03":{"매출액_QoQ":-10.8,"매출액_YoY":41.9,"매출총이익률":57.3,"매출총이익률_QoQ":4.9,"매출총이익률_YoY":18.7,"영업이익률":42.2,"영업이익률_QoQ":1.3,"영업이익률_YoY":19,"periodEndMonth":"2025-03"},"2025-06":{"매출액_QoQ":26,"매출액_YoY":35.4,"매출총이익률":53.9,"매출총이익률_QoQ":-3.4,"매출총이익률_YoY":8.3,"영업이익률":41.4,"영업이익률_QoQ":-0.8,"영업이익률_YoY":8.1,"periodEndMonth":"2025-06"},"2025-09":{"매출액_QoQ":10,"매출액_YoY":39.1,"매출총이익률":57.4,"매출총이익률_QoQ":3.5,"매출총이익률_YoY":5.2,"영업이익률":46.6,"영업이익률_QoQ":5.2,"영업이익률_YoY":6.6,"periodEndMonth":"2025-09"},"2025-12":{"매출액_QoQ":34.3,"매출액_YoY":66.1,"매출총이익률":68.8,"매출총이익률_QoQ":11.4,"매출총이익률_YoY":16.4,"영업이익률":58.4,"영업이익률_QoQ":11.8,"영업이익률_YoY":17.5,"periodEndMonth":"2025-12"}},"AMZN":{"2020-03":{"매출액_QoQ":null,"매출액_YoY":null,"매출총이익률":41.3,"매출총이익률_QoQ":null,"매출총이익률_YoY":null,"영업이익률":5.3,"영업이익률_QoQ":null,"영업이익률_YoY":null,"periodEndMonth":"2020-03"},"2020-06":{"매출액_QoQ":17.8,"매출액_YoY":null,"매출총이익률":40.8,"매출총이익률_QoQ":-0.5,"매출총이익률_YoY":null,"영업이익률":6.6,"영업이익률_QoQ":1.3,"영업이익률_YoY":null,"periodEndMonth":"2020-06"},"2020-09":{"매출액_QoQ":8.1,"매출액_YoY":null,"매출총이익률":40.6,"매출총이익률_QoQ":-0.2,"매출총이익률_YoY":null,"영업이익률":6.4,"영업이익률_QoQ":-0.2,"영업이익률_YoY":null,"periodEndMonth":"2020-09"},"2020-12":{"매출액_QoQ":30.6,"매출액_YoY":null,"매출총이익률":36.9,"매출총이익률_QoQ":-3.7,"매출총이익률_YoY":null,"영업이익률":5.5,"영업이익률_QoQ":-0.9,"영업이익률_YoY":null,"periodEndMonth":"2020-12"},"2021-03":{"매출액_QoQ":-13.6,"매출액_YoY":43.8,"매출총이익률":42.5,"매출총이익률_QoQ":5.6,"매출총이익률_YoY":1.2,"영업이익률":8.2,"영업이익률_QoQ":2.7,"영업이익률_YoY":2.9,"periodEndMonth":"2021-03"},"2021-06":{"매출액_QoQ":4.2,"매출액_YoY":27.2,"매출총이익률":43.2,"매출총이익률_QoQ":0.7,"매출총이익률_YoY":2.4,"영업이익률":6.8,"영업이익률_QoQ":-1.4,"영업이익률_YoY":0.2,"periodEndMonth":"2021-06"},"2021-09":{"매출액_QoQ":-2,"매출액_YoY":15.3,"매출총이익률":43.2,"매출총이익률_QoQ":0,"매출총이익률_YoY":2.6,"영업이익률":4.4,"영업이익률_QoQ":-2.4,"영업이익률_YoY":-2,"periodEndMonth":"2021-09"},"2021-12":{"매출액_QoQ":24,"매출액_YoY":9.4,"매출총이익률":39.7,"매출총이익률_QoQ":-3.5,"매출총이익률_YoY":2.8,"영업이익률":2.5,"영업이익률_QoQ":-1.9,"영업이익률_YoY":-3,"periodEndMonth":"2021-12"},"2022-03":{"매출액_QoQ":-15.3,"매출액_YoY":7.3,"매출총이익률":42.9,"매출총이익률_QoQ":3.2,"매출총이익률_YoY":0.4,"영업이익률":3.2,"영업이익률_QoQ":0.7,"영업이익률_YoY":-5,"periodEndMonth":"2022-03"},"2022-06":{"매출액_QoQ":4.1,"매출액_YoY":7.2,"매출총이익률":45.2,"매출총이익률_QoQ":2.3,"매출총이익률_YoY":2,"영업이익률":2.7,"영업이익률_QoQ":-0.5,"영업이익률_YoY":-4.1,"periodEndMonth":"2022-06"},"2022-09":{"매출액_QoQ":4.8,"매출액_YoY":14.7,"매출총이익률":44.7,"매출총이익률_QoQ":-0.5,"매출총이익률_YoY":1.5,"영업이익률":2,"영업이익률_QoQ":-0.7,"영업이익률_YoY":-2.4,"periodEndMonth":"2022-09"},"2022-12":{"매출액_QoQ":17.4,"매출액_YoY":8.6,"매출총이익률":42.6,"매출총이익률_QoQ":-2.1,"매출총이익률_YoY":2.9,"영업이익률":1.8,"영업이익률_QoQ":-0.2,"영업이익률_YoY":-0.7,"periodEndMonth":"2022-12"},"2023-03":{"매출액_QoQ":-14.6,"매출액_YoY":9.4,"매출총이익률":46.8,"매출총이익률_QoQ":4.2,"매출총이익률_YoY":3.9,"영업이익률":3.7,"영업이익률_QoQ":1.9,"영업이익률_YoY":0.5,"periodEndMonth":"2023-03"},"2023-06":{"매출액_QoQ":5.5,"매출액_YoY":10.8,"매출총이익률":48.4,"매출총이익률_QoQ":1.6,"매출총이익률_YoY":3.2,"영업이익률":5.7,"영업이익률_QoQ":2,"영업이익률_YoY":3,"periodEndMonth":"2023-06"},"2023-09":{"매출액_QoQ":6.5,"매출액_YoY":12.6,"매출총이익률":47.6,"매출총이익률_QoQ":-0.8,"매출총이익률_YoY":2.9,"영업이익률":7.8,"영업이익률_QoQ":2.1,"영업이익률_YoY":5.8,"periodEndMonth":"2023-09"},"2023-12":{"매출액_QoQ":18.8,"매출액_YoY":13.9,"매출총이익률":45.5,"매출총이익률_QoQ":-2.1,"매출총이익률_YoY":2.9,"영업이익률":7.8,"영업이익률_QoQ":0,"영업이익률_YoY":6,"periodEndMonth":"2023-12"},"2024-03":{"매출액_QoQ":-15.7,"매출액_YoY":12.5,"매출총이익률":49.3,"매출총이익률_QoQ":3.8,"매출총이익률_YoY":2.5,"영업이익률":10.7,"영업이익률_QoQ":2.9,"영업이익률_YoY":7,"periodEndMonth":"2024-03"},"2024-06":{"매출액_QoQ":3.3,"매출액_YoY":10.1,"매출총이익률":50.1,"매출총이익률_QoQ":0.8,"매출총이익률_YoY":1.7,"영업이익률":9.9,"영업이익률_QoQ":-0.8,"영업이익률_YoY":4.2,"periodEndMonth":"2024-06"},"2024-09":{"매출액_QoQ":7.4,"매출액_YoY":11,"매출총이익률":49,"매출총이익률_QoQ":-1.1,"매출총이익률_YoY":1.4,"영업이익률":11,"영업이익률_QoQ":1.1,"영업이익률_YoY":3.2,"periodEndMonth":"2024-09"},"2024-12":{"매출액_QoQ":18.2,"매출액_YoY":10.5,"매출총이익률":47.3,"매출총이익률_QoQ":-1.7,"매출총이익률_YoY":1.8,"영업이익률":11.3,"영업이익률_QoQ":0.3,"영업이익률_YoY":3.5,"periodEndMonth":"2024-12"},"2025-03":{"매출액_QoQ":-17.1,"매출액_YoY":8.6,"매출총이익률":50.6,"매출총이익률_QoQ":3.3,"매출총이익률_YoY":1.3,"영업이익률":11.8,"영업이익률_QoQ":0.5,"영업이익률_YoY":1.1,"periodEndMonth":"2025-03"},"2025-06":{"매출액_QoQ":7.7,"매출액_YoY":13.3,"매출총이익률":51.8,"매출총이익률_QoQ":1.2,"매출총이익률_YoY":1.7,"영업이익률":11.4,"영업이익률_QoQ":-0.4,"영업이익률_YoY":1.5,"periodEndMonth":"2025-06"},"2025-09":{"매출액_QoQ":7.4,"매출액_YoY":13.4,"매출총이익률":50.8,"매출총이익률_QoQ":-1,"매출총이익률_YoY":1.8,"영업이익률":9.7,"영업이익률_QoQ":-1.7,"영업이익률_YoY":-1.3,"periodEndMonth":"2025-09"},"2025-12":{"매출액_QoQ":18.4,"매출액_YoY":13.6,"매출총이익률":48.5,"매출총이익률_QoQ":-2.3,"매출총이익률_YoY":1.2,"영업이익률":11.7,"영업이익률_QoQ":2,"영업이익률_YoY":0.4,"periodEndMonth":"2025-12"}},"AVGO":{"2020-02":{"매출액_QoQ":null,"매출액_YoY":null,"매출총이익률":55.7,"매출총이익률_QoQ":null,"매출총이익률_YoY":null,"영업이익률":12.2,"영업이익률_QoQ":null,"영업이익률_YoY":null,"periodEndMonth":"2020-02"},"2020-05":{"매출액_QoQ":-2,"매출액_YoY":null,"매출총이익률":55.5,"매출총이익률_QoQ":-0.2,"매출총이익률_YoY":null,"영업이익률":13.3,"영업이익률_QoQ":1.1,"영업이익률_YoY":null,"periodEndMonth":"2020-05"},"2020-08":{"매출액_QoQ":1.4,"매출액_YoY":null,"매출총이익률":57,"매출총이익률_QoQ":1.5,"매출총이익률_YoY":null,"영업이익률":17.3,"영업이익률_QoQ":4,"영업이익률_YoY":null,"periodEndMonth":"2020-08"},"2020-11":{"매출액_QoQ":11.1,"매출액_YoY":null,"매출총이익률":57.9,"매출총이익률_QoQ":0.9,"매출총이익률_YoY":null,"영업이익률":23.6,"영업이익률_QoQ":6.3,"영업이익률_YoY":null,"periodEndMonth":"2020-11"},"2021-01":{"매출액_QoQ":2.9,"매출액_YoY":13.6,"매출총이익률":59.4,"매출총이익률_QoQ":1.5,"매출총이익률_YoY":3.7,"영업이익률":27.6,"영업이익률_QoQ":4,"영업이익률_YoY":15.4,"periodEndMonth":"2021-01"},"2021-05":{"매출액_QoQ":-0.7,"매출액_YoY":15.1,"매출총이익률":61.4,"매출총이익률_QoQ":2,"매출총이익률_YoY":5.9,"영업이익률":29.9,"영업이익률_QoQ":2.3,"영업이익률_YoY":16.6,"periodEndMonth":"2021-05"},"2021-08":{"매출액_QoQ":2.5,"매출액_YoY":16.4,"매출총이익률":61.9,"매출총이익률_QoQ":0.5,"매출총이익률_YoY":4.9,"영업이익률":31.4,"영업이익률_QoQ":1.5,"영업이익률_YoY":14.1,"periodEndMonth":"2021-08"},"2021-10":{"매출액_QoQ":9.3,"매출액_YoY":14.5,"매출총이익률":62.6,"매출총이익률_QoQ":0.7,"매출총이익률_YoY":4.7,"영업이익률":34.8,"영업이익률_QoQ":3.4,"영업이익률_YoY":11.2,"periodEndMonth":"2021-10"},"2022-01":{"매출액_QoQ":4,"매출액_YoY":15.8,"매출총이익률":65.5,"매출총이익률_QoQ":2.9,"매출총이익률_YoY":6.1,"영업이익률":40.3,"영업이익률_QoQ":5.5,"영업이익률_YoY":12.7,"periodEndMonth":"2022-01"},"2022-05":{"매출액_QoQ":5.2,"매출액_YoY":22.6,"매출총이익률":67.1,"매출총이익률_QoQ":1.6,"매출총이익률_YoY":5.7,"영업이익률":41.9,"영업이익률_QoQ":1.6,"영업이익률_YoY":12,"periodEndMonth":"2022-05"},"2022-07":{"매출액_QoQ":4.5,"매출액_YoY":24.9,"매출총이익률":67.1,"매출총이익률_QoQ":0,"매출총이익률_YoY":5.2,"영업이익률":44.2,"영업이익률_QoQ":2.3,"영업이익률_YoY":12.8,"periodEndMonth":"2022-07"},"2022-10":{"매출액_QoQ":5.5,"매출액_YoY":20.6,"매출총이익률":66.4,"매출총이익률_QoQ":-0.7,"매출총이익률_YoY":3.8,"영업이익률":44.6,"영업이익률_QoQ":0.4,"영업이익률_YoY":9.8,"periodEndMonth":"2022-10"},"2023-01":{"매출액_QoQ":-0.2,"매출액_YoY":15.7,"매출총이익률":67.3,"매출총이익률_QoQ":0.9,"매출총이익률_YoY":1.8,"영업이익률":46,"영업이익률_QoQ":1.4,"영업이익률_YoY":5.7,"periodEndMonth":"2023-01"},"2023-04":{"매출액_QoQ":-2,"매출액_YoY":7.8,"매출총이익률":70,"매출총이익률_QoQ":2.7,"매출총이익률_YoY":2.9,"영업이익률":45.9,"영업이익률_QoQ":-0.1,"영업이익률_YoY":4,"periodEndMonth":"2023-04"},"2023-07":{"매출액_QoQ":1.6,"매출액_YoY":4.9,"매출총이익률":69.4,"매출총이익률_QoQ":-0.6,"매출총이익률_YoY":2.3,"영업이익률":43.4,"영업이익률_QoQ":-2.5,"영업이익률_YoY":-0.8,"periodEndMonth":"2023-07"},"2023-10":{"매출액_QoQ":4.7,"매출액_YoY":4.1,"매출총이익률":68.9,"매출총이익률_QoQ":-0.5,"매출총이익률_YoY":2.5,"영업이익률":45.6,"영업이익률_QoQ":2.2,"영업이익률_YoY":1,"periodEndMonth":"2023-10"},"2024-02":{"매출액_QoQ":-4.1,"매출액_YoY":0,"매출총이익률":67.3,"매출총이익률_QoQ":-1.6,"매출총이익률_YoY":0,"영업이익률":46,"영업이익률_QoQ":0.4,"영업이익률_YoY":0,"periodEndMonth":"2024-02"},"2024-05":{"매출액_QoQ":74.2,"매출액_YoY":77.9,"매출총이익률":58.9,"매출총이익률_QoQ":-8.4,"매출총이익률_YoY":-11.1,"영업이익률":6.1,"영업이익률_QoQ":-39.9,"영업이익률_YoY":-39.8,"periodEndMonth":"2024-05"},"2024-08":{"매출액_QoQ":-15.8,"매출액_YoY":47.3,"매출총이익률":63.9,"매출총이익률_QoQ":5,"매출총이익률_YoY":-5.5,"영업이익률":29,"영업이익률_QoQ":22.9,"영업이익률_YoY":-14.4,"periodEndMonth":"2024-08"},"2024-11":{"매출액_QoQ":7.5,"매출액_YoY":51.2,"매출총이익률":64.1,"매출총이익률_QoQ":0.2,"매출총이익률_YoY":-4.8,"영업이익률":32.9,"영업이익률_QoQ":3.9,"영업이익률_YoY":-12.7,"periodEndMonth":"2024-11"},"2025-02":{"매출액_QoQ":6.1,"매출액_YoY":67.3,"매출총이익률":68,"매출총이익률_QoQ":3.9,"매출총이익률_YoY":0.7,"영업이익률":42,"영업이익률_QoQ":9.1,"영업이익률_YoY":-4,"periodEndMonth":"2025-02"},"2025-05":{"매출액_QoQ":0.6,"매출액_YoY":-3.4,"매출총이익률":68,"매출총이익률_QoQ":0,"매출총이익률_YoY":9.1,"영업이익률":38.8,"영업이익률_QoQ":-3.2,"영업이익률_YoY":32.7,"periodEndMonth":"2025-05"},"2025-08":{"매출액_QoQ":6.3,"매출액_YoY":22,"매출총이익률":67.1,"매출총이익률_QoQ":-0.9,"매출총이익률_YoY":3.2,"영업이익률":36.9,"영업이익률_QoQ":-1.9,"영업이익률_YoY":7.9,"periodEndMonth":"2025-08"},"2025-11":{"매출액_QoQ":12.9,"매출액_YoY":28.2,"매출총이익률":68,"매출총이익률_QoQ":0.9,"매출총이익률_YoY":3.9,"영업이익률":41.7,"영업이익률_QoQ":4.8,"영업이익률_YoY":8.8,"periodEndMonth":"2025-11"},"2026-02":{"매출액_QoQ":7.2,"매출액_YoY":29.5,"매출총이익률":75.8,"매출총이익률_QoQ":7.8,"매출총이익률_YoY":7.8,"영업이익률":44.9,"영업이익률_QoQ":3.2,"영업이익률_YoY":2.9,"periodEndMonth":"2026-02"}},"GOOGL":{"2020-03":{"매출액_QoQ":null,"매출액_YoY":null,"매출총이익률":54.1,"매출총이익률_QoQ":null,"매출총이익률_YoY":null,"영업이익률":19.5,"영업이익률_QoQ":null,"영업이익률_YoY":null,"periodEndMonth":"2020-03"},"2020-06":{"매출액_QoQ":-6.1,"매출액_YoY":null,"매출총이익률":51.3,"매출총이익률_QoQ":-2.8,"매출총이익률_YoY":null,"영업이익률":16.6,"영업이익률_QoQ":-2.9,"영업이익률_YoY":null,"periodEndMonth":"2020-06"},"2020-09":{"매출액_QoQ":20,"매출액_YoY":null,"매출총이익률":54.3,"매출총이익률_QoQ":3,"매출총이익률_YoY":null,"영업이익률":24.3,"영업이익률_QoQ":7.7,"영업이익률_YoY":null,"periodEndMonth":"2020-09"},"2020-12":{"매출액_QoQ":23.2,"매출액_YoY":null,"매출총이익률":54.2,"매출총이익률_QoQ":-0.1,"매출총이익률_YoY":null,"영업이익률":27.5,"영업이익률_QoQ":3.2,"영업이익률_YoY":null,"periodEndMonth":"2020-12"},"2021-03":{"매출액_QoQ":-2.8,"매출액_YoY":35,"매출총이익률":56.4,"매출총이익률_QoQ":2.2,"매출총이익률_YoY":2.3,"영업이익률":29.7,"영업이익률_QoQ":2.2,"영업이익률_YoY":10.2,"periodEndMonth":"2021-03"},"2021-06":{"매출액_QoQ":11.9,"매출액_YoY":60.8,"매출총이익률":57.6,"매출총이익률_QoQ":1.2,"매출총이익률_YoY":6.3,"영업이익률":31.3,"영업이익률_QoQ":1.6,"영업이익률_YoY":14.7,"periodEndMonth":"2021-06"},"2021-09":{"매출액_QoQ":5.2,"매출액_YoY":41,"매출총이익률":57.6,"매출총이익률_QoQ":0,"매출총이익률_YoY":3.3,"영업이익률":32.3,"영업이익률_QoQ":1,"영업이익률_YoY":8,"periodEndMonth":"2021-09"},"2021-12":{"매출액_QoQ":15.7,"매출액_YoY":32.4,"매출총이익률":56.2,"매출총이익률_QoQ":-1.4,"매출총이익률_YoY":2,"영업이익률":29.1,"영업이익률_QoQ":-3.2,"영업이익률_YoY":1.6,"periodEndMonth":"2021-12"},"2022-03":{"매출액_QoQ":-9.7,"매출액_YoY":23,"매출총이익률":56.5,"매출총이익률_QoQ":0.3,"매출총이익률_YoY":0.1,"영업이익률":29.5,"영업이익률_QoQ":0.4,"영업이익률_YoY":-0.2,"periodEndMonth":"2022-03"},"2022-06":{"매출액_QoQ":2.5,"매출액_YoY":12.6,"매출총이익률":56.8,"매출총이익률_QoQ":0.3,"매출총이익률_YoY":-0.8,"영업이익률":27.9,"영업이익률_QoQ":-1.6,"영업이익률_YoY":-3.4,"periodEndMonth":"2022-06"},"2022-09":{"매출액_QoQ":-0.9,"매출액_YoY":6.1,"매출총이익률":54.9,"매출총이익률_QoQ":-1.9,"매출총이익률_YoY":-2.7,"영업이익률":24.8,"영업이익률_QoQ":-3.1,"영업이익률_YoY":-7.5,"periodEndMonth":"2022-09"},"2022-12":{"매출액_QoQ":10.1,"매출액_YoY":1,"매출총이익률":53.5,"매출총이익률_QoQ":-1.4,"매출총이익률_YoY":-2.7,"영업이익률":23.9,"영업이익률_QoQ":-0.9,"영업이익률_YoY":-5.2,"periodEndMonth":"2022-12"},"2023-03":{"매출액_QoQ":-8.2,"매출액_YoY":2.6,"매출총이익률":56.1,"매출총이익률_QoQ":2.6,"매출총이익률_YoY":-0.4,"영업이익률":25,"영업이익률_QoQ":1.1,"영업이익률_YoY":-4.5,"periodEndMonth":"2023-03"},"2023-06":{"매출액_QoQ":6.9,"매출액_YoY":7.1,"매출총이익률":57.2,"매출총이익률_QoQ":1.1,"매출총이익률_YoY":0.4,"영업이익률":29.3,"영업이익률_QoQ":4.3,"영업이익률_YoY":1.4,"periodEndMonth":"2023-06"},"2023-09":{"매출액_QoQ":2.8,"매출액_YoY":11,"매출총이익률":56.7,"매출총이익률_QoQ":-0.5,"매출총이익률_YoY":1.8,"영업이익률":27.8,"영업이익률_QoQ":-1.5,"영업이익률_YoY":3,"periodEndMonth":"2023-09"},"2023-12":{"매출액_QoQ":12.5,"매출액_YoY":13.5,"매출총이익률":56.5,"매출총이익률_QoQ":-0.2,"매출총이익률_YoY":3,"영업이익률":27.5,"영업이익률_QoQ":-0.3,"영업이익률_YoY":3.6,"periodEndMonth":"2023-12"},"2024-03":{"매출액_QoQ":-6.7,"매출액_YoY":15.4,"매출총이익률":58.1,"매출총이익률_QoQ":1.6,"매출총이익률_YoY":2,"영업이익률":31.6,"영업이익률_QoQ":4.1,"영업이익률_YoY":6.6,"periodEndMonth":"2024-03"},"2024-06":{"매출액_QoQ":5.2,"매출액_YoY":13.6,"매출총이익률":58.1,"매출총이익률_QoQ":0,"매출총이익률_YoY":0.9,"영업이익률":32.4,"영업이익률_QoQ":0.8,"영업이익률_YoY":3.1,"periodEndMonth":"2024-06"},"2024-09":{"매출액_QoQ":4.2,"매출액_YoY":15.1,"매출총이익률":58.7,"매출총이익률_QoQ":0.6,"매출총이익률_YoY":2,"영업이익률":32.3,"영업이익률_QoQ":-0.1,"영업이익률_YoY":4.5,"periodEndMonth":"2024-09"},"2024-12":{"매출액_QoQ":9.3,"매출액_YoY":11.8,"매출총이익률":57.9,"매출총이익률_QoQ":-0.8,"매출총이익률_YoY":1.4,"영업이익률":32.1,"영업이익률_QoQ":-0.2,"영업이익률_YoY":4.6,"periodEndMonth":"2024-12"},"2025-03":{"매출액_QoQ":-6.5,"매출액_YoY":12,"매출총이익률":59.7,"매출총이익률_QoQ":1.8,"매출총이익률_YoY":1.6,"영업이익률":33.9,"영업이익률_QoQ":1.8,"영업이익률_YoY":2.3,"periodEndMonth":"2025-03"},"2025-06":{"매출액_QoQ":6.9,"매출액_YoY":13.8,"매출총이익률":59.5,"매출총이익률_QoQ":-0.2,"매출총이익률_YoY":1.4,"영업이익률":32.4,"영업이익률_QoQ":-1.5,"영업이익률_YoY":0,"periodEndMonth":"2025-06"},"2025-09":{"매출액_QoQ":6.1,"매출액_YoY":15.9,"매출총이익률":59.6,"매출총이익률_QoQ":0.1,"매출총이익률_YoY":0.9,"영업이익률":30.5,"영업이익률_QoQ":-1.9,"영업이익률_YoY":-1.8,"periodEndMonth":"2025-09"},"2025-12":{"매출액_QoQ":11.2,"매출액_YoY":18,"매출총이익률":59.8,"매출총이익률_QoQ":0.2,"매출총이익률_YoY":1.9,"영업이익률":31.6,"영업이익률_QoQ":1.1,"영업이익률_YoY":-0.5,"periodEndMonth":"2025-12"}},"MRVL":{"2021-05":{"매출액_QoQ":null,"매출액_YoY":null,"매출총이익률":50.2,"매출총이익률_QoQ":null,"매출총이익률_YoY":null,"영업이익률":-9.9,"영업이익률_QoQ":null,"영업이익률_YoY":null,"periodEndMonth":"2021-05"},"2021-07":{"매출액_QoQ":29.3,"매출액_YoY":null,"매출총이익률":34.6,"매출총이익률_QoQ":-15.6,"매출총이익률_YoY":null,"영업이익률":-24.8,"영업이익률_QoQ":-14.9,"영업이익률_YoY":null,"periodEndMonth":"2021-07"},"2021-10":{"매출액_QoQ":12.5,"매출액_YoY":null,"매출총이익률":48.6,"매출총이익률_QoQ":14,"매출총이익률_YoY":null,"영업이익률":-2.7,"영업이익률_QoQ":22.1,"영업이익률_YoY":null,"periodEndMonth":"2021-10"},"2022-01":{"매출액_QoQ":10.9,"매출액_YoY":null,"매출총이익률":51.1,"매출총이익률_QoQ":2.5,"매출총이익률_YoY":null,"영업이익률":2.6,"영업이익률_QoQ":5.3,"영업이익률_YoY":null,"periodEndMonth":"2022-01"},"2022-04":{"매출액_QoQ":7.7,"매출액_YoY":73.9,"매출총이익률":51.9,"매출총이익률_QoQ":0.8,"매출총이익률_YoY":1.7,"영업이익률":4.8,"영업이익률_QoQ":2.2,"영업이익률_YoY":14.7,"periodEndMonth":"2022-04"},"2022-07":{"매출액_QoQ":4.8,"매출액_YoY":41,"매출총이익률":51.8,"매출총이익률_QoQ":-0.1,"매출총이익률_YoY":17.2,"영업이익률":2.6,"영업이익률_QoQ":-2.2,"영업이익률_YoY":27.4,"periodEndMonth":"2022-07"},"2022-10":{"매출액_QoQ":1.3,"매출액_YoY":26.9,"매출총이익률":50.6,"매출총이익률_QoQ":-1.2,"매출총이익률_YoY":2,"영업이익률":6.9,"영업이익률_QoQ":4.3,"영업이익률_YoY":9.6,"periodEndMonth":"2022-10"},"2023-01":{"매출액_QoQ":-7.7,"매출액_YoY":5.7,"매출총이익률":47.4,"매출총이익률_QoQ":-3.2,"매출총이익률_YoY":-3.7,"영업이익률":1.6,"영업이익률_QoQ":-5.3,"영업이익률_YoY":-1,"periodEndMonth":"2023-01"},"2023-04":{"매출액_QoQ":-6.8,"매출액_YoY":-8.6,"매출총이익률":42.1,"매출총이익률_QoQ":-5.3,"매출총이익률_YoY":-9.8,"영업이익률":-13.8,"영업이익률_QoQ":-15.4,"영업이익률_YoY":-18.6,"periodEndMonth":"2023-04"},"2023-07":{"매출액_QoQ":1.4,"매출액_YoY":-11.6,"매출총이익률":38.9,"매출총이익률_QoQ":-3.2,"매출총이익률_YoY":-12.9,"영업이익률":-15.4,"영업이익률_QoQ":-1.6,"영업이익률_YoY":-18,"periodEndMonth":"2023-07"},"2023-10":{"매출액_QoQ":5.8,"매출액_YoY":-7.7,"매출총이익률":38.9,"매출총이익률_QoQ":0,"매출총이익률_YoY":-11.7,"영업이익률":-10.1,"영업이익률_QoQ":5.3,"영업이익률_YoY":-17,"periodEndMonth":"2023-10"},"2024-02":{"매출액_QoQ":0.6,"매출액_YoY":0.5,"매출총이익률":46.6,"매출총이익률_QoQ":7.7,"매출총이익률_YoY":-0.8,"영업이익률":-0.5,"영업이익률_QoQ":9.6,"영업이익률_YoY":-2.1,"periodEndMonth":"2024-02"},"2024-05":{"매출액_QoQ":-18.6,"매출액_YoY":-12.2,"매출총이익률":45.5,"매출총이익률_QoQ":-1.1,"매출총이익률_YoY":3.4,"영업이익률":-12.8,"영업이익률_QoQ":-12.3,"영업이익률_YoY":1,"periodEndMonth":"2024-05"},"2024-08":{"매출액_QoQ":9.6,"매출액_YoY":-5.1,"매출총이익률":46.2,"매출총이익률_QoQ":0.7,"매출총이익률_YoY":7.3,"영업이익률":-7.6,"영업이익률_QoQ":5.2,"영업이익률_YoY":7.8,"periodEndMonth":"2024-08"},"2024-11":{"매출액_QoQ":19.1,"매출액_YoY":6.9,"매출총이익률":46.6,"매출총이익률_QoQ":0.4,"매출총이익률_YoY":7.7,"영업이익률":0.8,"영업이익률_QoQ":8.4,"영업이익률_YoY":10.9,"periodEndMonth":"2024-11"},"2025-02":{"매출액_QoQ":19.9,"매출액_YoY":27.4,"매출총이익률":50.5,"매출총이익률_QoQ":3.9,"매출총이익률_YoY":3.9,"영업이익률":12.3,"영업이익률_QoQ":11.5,"영업이익률_YoY":12.8,"periodEndMonth":"2025-02"},"2025-05":{"매출액_QoQ":4.3,"매출액_YoY":63.3,"매출총이익률":50.3,"매출총이익률_QoQ":-0.2,"매출총이익률_YoY":4.8,"영업이익률":13.6,"영업이익률_QoQ":1.3,"영업이익률_YoY":26.4,"periodEndMonth":"2025-05"},"2025-08":{"매출액_QoQ":5.8,"매출액_YoY":57.6,"매출총이익률":50.4,"매출총이익률_QoQ":0.1,"매출총이익률_YoY":4.2,"영업이익률":14.9,"영업이익률_QoQ":1.3,"영업이익률_YoY":22.5,"periodEndMonth":"2025-08"},"2025-11":{"매출액_QoQ":3.4,"매출액_YoY":36.8,"매출총이익률":51.6,"매출총이익률_QoQ":1.2,"매출총이익률_YoY":5,"영업이익률":17.7,"영업이익률_QoQ":2.8,"영업이익률_YoY":16.9,"periodEndMonth":"2025-11"},"2026-01":{"매출액_QoQ":7,"매출액_YoY":22.1,"매출총이익률":51.7,"매출총이익률_QoQ":0.1,"매출총이익률_YoY":1.2,"영업이익률":18.7,"영업이익률_QoQ":1,"영업이익률_YoY":6.4,"periodEndMonth":"2026-01"}},"MSFT":{"2019-09":{"매출액_QoQ":null,"매출액_YoY":null,"매출총이익률":68.5,"매출총이익률_QoQ":null,"매출총이익률_YoY":null,"영업이익률":38.4,"영업이익률_QoQ":null,"영업이익률_YoY":null,"periodEndMonth":"2019-09"},"2019-12":{"매출액_QoQ":11.7,"매출액_YoY":null,"매출총이익률":66.5,"매출총이익률_QoQ":-2,"매출총이익률_YoY":null,"영업이익률":37.6,"영업이익률_QoQ":-0.8,"영업이익률_YoY":null,"periodEndMonth":"2019-12"},"2020-03":{"매출액_QoQ":-5.1,"매출액_YoY":null,"매출총이익률":68.7,"매출총이익률_QoQ":2.2,"매출총이익률_YoY":null,"영업이익률":37,"영업이익률_QoQ":-0.6,"영업이익률_YoY":null,"periodEndMonth":"2020-03"},"2020-06":{"매출액_QoQ":8.6,"매출액_YoY":null,"매출총이익률":67.6,"매출총이익률_QoQ":-1.1,"매출총이익률_YoY":null,"영업이익률":35.3,"영업이익률_QoQ":-1.7,"영업이익률_YoY":null,"periodEndMonth":"2020-06"},"2020-09":{"매출액_QoQ":-2.3,"매출액_YoY":12.4,"매출총이익률":70.4,"매출총이익률_QoQ":2.8,"매출총이익률_YoY":1.9,"영업이익률":42.7,"영업이익률_QoQ":7.4,"영업이익률_YoY":4.3,"periodEndMonth":"2020-09"},"2020-12":{"매출액_QoQ":15.9,"매출액_YoY":16.7,"매출총이익률":67,"매출총이익률_QoQ":-3.4,"매출총이익률_YoY":0.5,"영업이익률":41.5,"영업이익률_QoQ":-1.2,"영업이익률_YoY":3.9,"periodEndMonth":"2020-12"},"2021-03":{"매출액_QoQ":-3.2,"매출액_YoY":19.1,"매출총이익률":68.7,"매출총이익률_QoQ":1.7,"매출총이익률_YoY":0,"영업이익률":40.9,"영업이익률_QoQ":-0.6,"영업이익률_YoY":3.9,"periodEndMonth":"2021-03"},"2021-06":{"매출액_QoQ":10.7,"매출액_YoY":21.3,"매출총이익률":69.7,"매출총이익률_QoQ":1,"매출총이익률_YoY":2.1,"영업이익률":41.4,"영업이익률_QoQ":0.5,"영업이익률_YoY":6.1,"periodEndMonth":"2021-06"},"2021-09":{"매출액_QoQ":-1.8,"매출액_YoY":22,"매출총이익률":69.9,"매출총이익률_QoQ":0.2,"매출총이익률_YoY":-0.5,"영업이익률":44.7,"영업이익률_QoQ":3.3,"영업이익률_YoY":2,"periodEndMonth":"2021-09"},"2021-12":{"매출액_QoQ":14.1,"매출액_YoY":20.1,"매출총이익률":67.2,"매출총이익률_QoQ":-2.7,"매출총이익률_YoY":0.2,"영업이익률":43,"영업이익률_QoQ":-1.7,"영업이익률_YoY":1.5,"periodEndMonth":"2021-12"},"2022-03":{"매출액_QoQ":-4.6,"매출액_YoY":18.4,"매출총이익률":68.4,"매출총이익률_QoQ":1.2,"매출총이익률_YoY":-0.3,"영업이익률":41.3,"영업이익률_QoQ":-1.7,"영업이익률_YoY":0.4,"periodEndMonth":"2022-03"},"2022-06":{"매출액_QoQ":5.1,"매출액_YoY":12.4,"매출총이익률":68.3,"매출총이익률_QoQ":-0.1,"매출총이익률_YoY":-1.4,"영업이익률":39.6,"영업이익률_QoQ":-1.7,"영업이익률_YoY":-1.8,"periodEndMonth":"2022-06"},"2022-09":{"매출액_QoQ":-3.4,"매출액_YoY":10.6,"매출총이익률":69.2,"매출총이익률_QoQ":0.9,"매출총이익률_YoY":-0.7,"영업이익률":42.9,"영업이익률_QoQ":3.3,"영업이익률_YoY":-1.8,"periodEndMonth":"2022-09"},"2022-12":{"매출액_QoQ":5.2,"매출액_YoY":2,"매출총이익률":66.8,"매출총이익률_QoQ":-2.4,"매출총이익률_YoY":-0.4,"영업이익률":38.7,"영업이익률_QoQ":-4.2,"영업이익률_YoY":-4.3,"periodEndMonth":"2022-12"},"2023-03":{"매출액_QoQ":0.2,"매출액_YoY":7.1,"매출총이익률":69.5,"매출총이익률_QoQ":2.7,"매출총이익률_YoY":1.1,"영업이익률":42.3,"영업이익률_QoQ":3.6,"영업이익률_YoY":1,"periodEndMonth":"2023-03"},"2023-06":{"매출액_QoQ":6.3,"매출액_YoY":8.3,"매출총이익률":70.1,"매출총이익률_QoQ":0.6,"매출총이익률_YoY":1.8,"영업이익률":43.2,"영업이익률_QoQ":0.9,"영업이익률_YoY":3.6,"periodEndMonth":"2023-06"},"2023-09":{"매출액_QoQ":0.6,"매출액_YoY":12.8,"매출총이익률":71.2,"매출총이익률_QoQ":1.1,"매출총이익률_YoY":2,"영업이익률":47.6,"영업이익률_QoQ":4.4,"영업이익률_YoY":4.7,"periodEndMonth":"2023-09"},"2023-12":{"매출액_QoQ":9.7,"매출액_YoY":17.6,"매출총이익률":68.4,"매출총이익률_QoQ":-2.8,"매출총이익률_YoY":1.6,"영업이익률":43.6,"영업이익률_QoQ":-4,"영업이익률_YoY":4.9,"periodEndMonth":"2023-12"},"2024-03":{"매출액_QoQ":-0.3,"매출액_YoY":17,"매출총이익률":70.1,"매출총이익률_QoQ":1.7,"매출총이익률_YoY":0.6,"영업이익률":44.6,"영업이익률_QoQ":1,"영업이익률_YoY":2.3,"periodEndMonth":"2024-03"},"2024-06":{"매출액_QoQ":4.6,"매출액_YoY":15.2,"매출총이익률":69.6,"매출총이익률_QoQ":-0.5,"매출총이익률_YoY":-0.5,"영업이익률":43.1,"영업이익률_QoQ":-1.5,"영업이익률_YoY":-0.1,"periodEndMonth":"2024-06"},"2024-09":{"매출액_QoQ":1.3,"매출액_YoY":16,"매출총이익률":69.4,"매출총이익률_QoQ":-0.2,"매출총이익률_YoY":-1.8,"영업이익률":46.6,"영업이익률_QoQ":3.5,"영업이익률_YoY":-1,"periodEndMonth":"2024-09"},"2024-12":{"매출액_QoQ":6.2,"매출액_YoY":12.3,"매출총이익률":68.7,"매출총이익률_QoQ":-0.7,"매출총이익률_YoY":0.3,"영업이익률":45.5,"영업이익률_QoQ":-1.1,"영업이익률_YoY":1.9,"periodEndMonth":"2024-12"},"2025-03":{"매출액_QoQ":0.6,"매출액_YoY":13.3,"매출총이익률":68.7,"매출총이익률_QoQ":0,"매출총이익률_YoY":-1.4,"영업이익률":45.7,"영업이익률_QoQ":0.2,"영업이익률_YoY":1.1,"periodEndMonth":"2025-03"},"2025-06":{"매출액_QoQ":9.1,"매출액_YoY":18.1,"매출총이익률":68.6,"매출총이익률_QoQ":-0.1,"매출총이익률_YoY":-1,"영업이익률":44.9,"영업이익률_QoQ":-0.8,"영업이익률_YoY":1.8,"periodEndMonth":"2025-06"},"2025-09":{"매출액_QoQ":1.6,"매출액_YoY":18.4,"매출총이익률":69,"매출총이익률_QoQ":0.4,"매출총이익률_YoY":-0.4,"영업이익률":48.9,"영업이익률_QoQ":4,"영업이익률_YoY":2.3,"periodEndMonth":"2025-09"},"2025-12":{"매출액_QoQ":4.6,"매출액_YoY":16.7,"매출총이익률":68,"매출총이익률_QoQ":-1,"매출총이익률_YoY":-0.7,"영업이익률":47.1,"영업이익률_QoQ":-1.8,"영업이익률_YoY":1.6,"periodEndMonth":"2025-12"}},"MU":{"2019-11":{"매출액_QoQ":null,"매출액_YoY":null,"매출총이익률":26.6,"매출총이익률_QoQ":null,"매출총이익률_YoY":null,"영업이익률":10.1,"영업이익률_QoQ":null,"영업이익률_YoY":null,"periodEndMonth":"2019-11"},"2020-02":{"매출액_QoQ":-6.7,"매출액_YoY":null,"매출총이익률":28.2,"매출총이익률_QoQ":1.6,"매출총이익률_YoY":null,"영업이익률":9.2,"영업이익률_QoQ":-0.9,"영업이익률_YoY":null,"periodEndMonth":"2020-02"},"2020-05":{"매출액_QoQ":13.4,"매출액_YoY":null,"매출총이익률":32.4,"매출총이익률_QoQ":4.2,"매출총이익률_YoY":null,"영업이익률":16.3,"영업이익률_QoQ":7.1,"영업이익률_YoY":null,"periodEndMonth":"2020-05"},"2020-09":{"매출액_QoQ":11.4,"매출액_YoY":17.7,"매출총이익률":34.1,"매출총이익률_QoQ":1.7,"매출총이익률_YoY":7.5,"영업이익률":19.1,"영업이익률_QoQ":2.8,"영업이익률_YoY":9,"periodEndMonth":"2020-09"},"2020-12":{"매출액_QoQ":-4.7,"매출액_YoY":12.2,"매출총이익률":30.1,"매출총이익률_QoQ":-4,"매출총이익률_YoY":3.5,"영업이익률":15,"영업이익률_QoQ":-4.1,"영업이익률_YoY":4.9,"periodEndMonth":"2020-12"},"2021-03":{"매출액_QoQ":108,"매출액_YoY":150.3,"매출총이익률":28.2,"매출총이익률_QoQ":-1.9,"매출총이익률_YoY":0,"영업이익률":12.7,"영업이익률_QoQ":-2.3,"영업이익률_YoY":3.5,"periodEndMonth":"2021-03"},"2021-06":{"매출액_QoQ":-90.1,"매출액_YoY":-78.2,"매출총이익률":124.5,"매출총이익률_QoQ":96.3,"매출총이익률_YoY":92.1,"영업이익률":95.8,"영업이익률_QoQ":83.1,"영업이익률_YoY":79.5,"periodEndMonth":"2021-06"},"2021-09":{"매출액_QoQ":597.6,"매출액_YoY":36.6,"매출총이익률":47.3,"매출총이익률_QoQ":-77.2,"매출총이익률_YoY":13.2,"영업이익률":35.7,"영업이익률_QoQ":-60.1,"영업이익률_YoY":16.6,"periodEndMonth":"2021-09"},"2021-12":{"매출액_QoQ":-7.1,"매출액_YoY":33.2,"매출총이익률":46.4,"매출총이익률_QoQ":-0.9,"매출총이익률_YoY":16.3,"영업이익률":34.2,"영업이익률_QoQ":-1.5,"영업이익률_YoY":19.2,"periodEndMonth":"2021-12"},"2022-03":{"매출액_QoQ":1.3,"매출액_YoY":-35.2,"매출총이익률":47.2,"매출총이익률_QoQ":0.8,"매출총이익률_YoY":19,"영업이익률":32.7,"영업이익률_QoQ":-1.5,"영업이익률_YoY":20,"periodEndMonth":"2022-03"},"2022-06":{"매출액_QoQ":11,"매출액_YoY":628.7,"매출총이익률":46.7,"매출총이익률_QoQ":-0.5,"매출총이익률_YoY":-77.8,"영업이익률":34.8,"영업이익률_QoQ":2.1,"영업이익률_YoY":-61,"periodEndMonth":"2022-06"},"2022-09":{"매출액_QoQ":-23.1,"매출액_YoY":-19.7,"매출총이익률":39.5,"매출총이익률_QoQ":-7.2,"매출총이익률_YoY":-7.8,"영업이익률":22.9,"영업이익률_QoQ":-11.9,"영업이익률_YoY":-12.8,"periodEndMonth":"2022-09"},"2022-12":{"매출액_QoQ":-38.5,"매출액_YoY":-46.9,"매출총이익률":21.9,"매출총이익률_QoQ":-17.6,"매출총이익률_YoY":-24.5,"영업이익률":-5.1,"영업이익률_QoQ":-28,"영업이익률_YoY":-39.3,"periodEndMonth":"2022-12"},"2023-03":{"매출액_QoQ":-9.6,"매출액_YoY":-52.6,"매출총이익률":-32.7,"매출총이익률_QoQ":-54.6,"매출총이익률_YoY":-79.9,"영업이익률":-62.4,"영업이익률_QoQ":-57.3,"영업이익률_YoY":-95.1,"periodEndMonth":"2023-03"},"2023-06":{"매출액_QoQ":1.6,"매출액_YoY":-56.6,"매출총이익률":-17.8,"매출총이익률_QoQ":14.9,"매출총이익률_YoY":-64.5,"영업이익률":-46.9,"영업이익률_QoQ":15.5,"영업이익률_YoY":-81.7,"periodEndMonth":"2023-06"},"2023-08":{"매출액_QoQ":6.9,"매출액_YoY":-39.6,"매출총이익률":-10.8,"매출총이익률_QoQ":7,"매출총이익률_YoY":-50.3,"영업이익률":-36.7,"영업이익률_QoQ":10.2,"영업이익률_YoY":-59.6,"periodEndMonth":"2023-08"},"2023-11":{"매출액_QoQ":17.9,"매출액_YoY":15.7,"매출총이익률":-0.7,"매출총이익률_QoQ":10.1,"매출총이익률_YoY":-22.6,"영업이익률":-23.9,"영업이익률_QoQ":12.8,"영업이익률_YoY":-18.8,"periodEndMonth":"2023-11"},"2024-02":{"매출액_QoQ":23.2,"매출액_YoY":57.7,"매출총이익률":18.5,"매출총이익률_QoQ":19.2,"매출총이익률_YoY":51.2,"영업이익률":3.3,"영업이익률_QoQ":27.2,"영업이익률_YoY":65.7,"periodEndMonth":"2024-02"},"2024-05":{"매출액_QoQ":16.9,"매출액_YoY":81.5,"매출총이익률":26.9,"매출총이익률_QoQ":8.4,"매출총이익률_YoY":44.7,"영업이익률":10.6,"영업이익률_QoQ":7.3,"영업이익률_YoY":57.5,"periodEndMonth":"2024-05"},"2024-08":{"매출액_QoQ":13.8,"매출액_YoY":93.3,"매출총이익률":35.3,"매출총이익률_QoQ":8.4,"매출총이익률_YoY":46.1,"영업이익률":19.6,"영업이익률_QoQ":9,"영업이익률_YoY":56.3,"periodEndMonth":"2024-08"},"2024-11":{"매출액_QoQ":12.4,"매출액_YoY":84.3,"매출총이익률":38.4,"매출총이익률_QoQ":3.1,"매출총이익률_YoY":39.1,"영업이익률":25,"영업이익률_QoQ":5.4,"영업이익률_YoY":48.9,"periodEndMonth":"2024-11"},"2025-02":{"매출액_QoQ":-7.5,"매출액_YoY":38.3,"매출총이익률":36.8,"매출총이익률_QoQ":-1.6,"매출총이익률_YoY":18.3,"영업이익률":22,"영업이익률_QoQ":-3,"영업이익률_YoY":18.7,"periodEndMonth":"2025-02"},"2025-05":{"매출액_QoQ":15.5,"매출액_YoY":36.6,"매출총이익률":37.7,"매출총이익률_QoQ":0.9,"매출총이익률_YoY":10.8,"영업이익률":23.3,"영업이익률_QoQ":1.3,"영업이익률_YoY":12.7,"periodEndMonth":"2025-05"},"2025-08":{"매출액_QoQ":21.7,"매출액_YoY":46,"매출총이익률":44.7,"매출총이익률_QoQ":7,"매출총이익률_YoY":9.4,"영업이익률":32.3,"영업이익률_QoQ":9,"영업이익률_YoY":12.7,"periodEndMonth":"2025-08"},"2025-11":{"매출액_QoQ":20.6,"매출액_YoY":56.7,"매출총이익률":56,"매출총이익률_QoQ":11.3,"매출총이익률_YoY":17.6,"영업이익률":45,"영업이익률_QoQ":12.7,"영업이익률_YoY":20,"periodEndMonth":"2025-11"},"2026-02":{"매출액_QoQ":74.9,"매출액_YoY":196.3,"매출총이익률":74.4,"매출총이익률_QoQ":18.4,"매출총이익률_YoY":37.6,"영업이익률":67.6,"영업이익률_QoQ":22.6,"영업이익률_YoY":45.6,"periodEndMonth":"2026-02"}},"NVDA":{"2019-07":{"매출액_QoQ":null,"매출액_YoY":null,"매출총이익률":59.8,"매출총이익률_QoQ":null,"매출총이익률_YoY":null,"영업이익률":22.1,"영업이익률_QoQ":null,"영업이익률_YoY":null,"periodEndMonth":"2019-07"},"2019-10":{"매출액_QoQ":16.9,"매출액_YoY":null,"매출총이익률":63.6,"매출총이익률_QoQ":3.8,"매출총이익률_YoY":null,"영업이익률":30.8,"영업이익률_QoQ":8.7,"영업이익률_YoY":null,"periodEndMonth":"2019-10"},"2020-01":{"매출액_QoQ":3,"매출액_YoY":null,"매출총이익률":64.9,"매출총이익률_QoQ":1.3,"매출총이익률_YoY":null,"영업이익률":31.9,"영업이익률_QoQ":1.1,"영업이익률_YoY":null,"periodEndMonth":"2020-01"},"2020-04":{"매출액_QoQ":-0.8,"매출액_YoY":null,"매출총이익률":65.1,"매출총이익률_QoQ":0.2,"매출총이익률_YoY":null,"영업이익률":31.7,"영업이익률_QoQ":-0.2,"영업이익률_YoY":null,"periodEndMonth":"2020-04"},"2020-10":{"매출액_QoQ":279,"매출액_YoY":287.3,"매출총이익률":62,"매출총이익률_QoQ":-3.1,"매출총이익률_YoY":-1.6,"영업이익률":25.9,"영업이익률_QoQ":-5.8,"영업이익률_YoY":-4.9,"periodEndMonth":"2020-10"},"2021-05":{"매출액_QoQ":-51.5,"매출액_YoY":83.8,"매출총이익률":64.1,"매출총이익률_QoQ":2.1,"매출총이익률_YoY":-1,"영업이익률":34.6,"영업이익률_QoQ":8.7,"영업이익률_YoY":2.9,"periodEndMonth":"2021-05"},"2021-08":{"매출액_QoQ":14.9,"매출액_YoY":-44.3,"매출총이익률":64.8,"매출총이익률_QoQ":0.7,"매출총이익률_YoY":2.8,"영업이익률":37.6,"영업이익률_QoQ":3,"영업이익률_YoY":11.7,"periodEndMonth":"2021-08"},"2021-10":{"매출액_QoQ":9.2,"매출액_YoY":-39.1,"매출총이익률":65.2,"매출총이익률_QoQ":0.4,"매출총이익률_YoY":3.2,"영업이익률":37.6,"영업이익률_QoQ":0,"영업이익률_YoY":11.7,"periodEndMonth":"2021-10"},"2022-01":{"매출액_QoQ":7.6,"매출액_YoY":null,"매출총이익률":65.4,"매출총이익률_QoQ":0.2,"매출총이익률_YoY":null,"영업이익률":38.9,"영업이익률_QoQ":1.3,"영업이익률_YoY":null,"periodEndMonth":"2022-01"},"2022-05":{"매출액_QoQ":8.4,"매출액_YoY":46.4,"매출총이익률":65.5,"매출총이익률_QoQ":0.1,"매출총이익률_YoY":1.4,"영업이익률":22.5,"영업이익률_QoQ":-16.4,"영업이익률_YoY":-12.1,"periodEndMonth":"2022-05"},"2022-07":{"매출액_QoQ":-119.1,"매출액_YoY":-124.3,"매출총이익률":158.8,"매출총이익률_QoQ":93.3,"매출총이익률_YoY":94,"영업이익률":86.4,"영업이익률_QoQ":63.9,"영업이익률_YoY":48.8,"periodEndMonth":"2022-07"},"2022-10":{"매출액_QoQ":51.2,"매출액_YoY":-110.9,"매출총이익률":-33.9,"매출총이익률_QoQ":-192.7,"매출총이익률_YoY":-99.1,"영업이익률":-13.2,"영업이익률_QoQ":-99.6,"영업이익률_YoY":-50.8,"periodEndMonth":"2022-10"},"2023-01":{"매출액_QoQ":882.8,"매출액_YoY":-20.8,"매출총이익률":63.3,"매출총이익률_QoQ":97.2,"매출총이익률_YoY":-2.1,"영업이익률":20.8,"영업이익률_QoQ":34,"영업이익률_YoY":-18.1,"periodEndMonth":"2023-01"},"2023-04":{"매출액_QoQ":18.9,"매출액_YoY":-13.2,"매출총이익률":64.6,"매출총이익률_QoQ":1.3,"매출총이익률_YoY":-0.9,"영업이익률":29.8,"영업이익률_QoQ":9,"영업이익률_YoY":7.3,"periodEndMonth":"2023-04"},"2023-07":{"매출액_QoQ":87.8,"매출액_YoY":952.7,"매출총이익률":70.1,"매출총이익률_QoQ":5.5,"매출총이익률_YoY":-88.7,"영업이익률":50.4,"영업이익률_QoQ":20.6,"영업이익률_YoY":-36,"periodEndMonth":"2023-07"},"2023-10":{"매출액_QoQ":34.2,"매출액_YoY":2444.1,"매출총이익률":74,"매출총이익률_QoQ":3.9,"매출총이익률_YoY":107.9,"영업이익률":57.5,"영업이익률_QoQ":7.1,"영업이익률_YoY":70.7,"periodEndMonth":"2023-10"},"2024-01":{"매출액_QoQ":22,"매출액_YoY":265.3,"매출총이익률":76,"매출총이익률_QoQ":2,"매출총이익률_YoY":12.7,"영업이익률":61.6,"영업이익률_QoQ":4.1,"영업이익률_YoY":40.8,"periodEndMonth":"2024-01"},"2024-04":{"매출액_QoQ":17.8,"매출액_YoY":262.1,"매출총이익률":78.4,"매출총이익률_QoQ":2.4,"매출총이익률_YoY":13.8,"영업이익률":64.9,"영업이익률_QoQ":3.3,"영업이익률_YoY":35.1,"periodEndMonth":"2024-04"},"2024-07":{"매출액_QoQ":15.3,"매출액_YoY":122.4,"매출총이익률":75.1,"매출총이익률_QoQ":-3.3,"매출총이익률_YoY":5,"영업이익률":62.1,"영업이익률_QoQ":-2.8,"영업이익률_YoY":11.7,"periodEndMonth":"2024-07"},"2024-10":{"매출액_QoQ":16.8,"매출액_YoY":93.6,"매출총이익률":74.6,"매출총이익률_QoQ":-0.5,"매출총이익률_YoY":0.6,"영업이익률":62.3,"영업이익률_QoQ":0.2,"영업이익률_YoY":4.8,"periodEndMonth":"2024-10"},"2025-01":{"매출액_QoQ":12.1,"매출액_YoY":77.9,"매출총이익률":73,"매출총이익률_QoQ":-1.6,"매출총이익률_YoY":-3,"영업이익률":61.1,"영업이익률_QoQ":-1.2,"영업이익률_YoY":-0.5,"periodEndMonth":"2025-01"},"2025-04":{"매출액_QoQ":12,"매출액_YoY":69.2,"매출총이익률":60.5,"매출총이익률_QoQ":-12.5,"매출총이익률_YoY":-17.9,"영업이익률":49.1,"영업이익률_QoQ":-12,"영업이익률_YoY":-15.8,"periodEndMonth":"2025-04"},"2025-07":{"매출액_QoQ":6.1,"매출액_YoY":55.6,"매출총이익률":72.4,"매출총이익률_QoQ":11.9,"매출총이익률_YoY":-2.7,"영업이익률":60.8,"영업이익률_QoQ":11.7,"영업이익률_YoY":-1.3,"periodEndMonth":"2025-07"},"2025-10":{"매출액_QoQ":22,"매출액_YoY":62.5,"매출총이익률":73.4,"매출총이익률_QoQ":1,"매출총이익률_YoY":-1.2,"영업이익률":63.2,"영업이익률_QoQ":2.4,"영업이익률_YoY":0.9,"periodEndMonth":"2025-10"},"2026-01":{"매출액_QoQ":19.5,"매출액_YoY":73.2,"매출총이익률":75,"매출총이익률_QoQ":1.6,"매출총이익률_YoY":2,"영업이익률":65,"영업이익률_QoQ":1.8,"영업이익률_YoY":3.9,"periodEndMonth":"2026-01"}},"ORCL":{"2019-08":{"매출액_QoQ":null,"매출액_YoY":null,"매출총이익률":31.2,"매출총이익률_QoQ":null,"매출총이익률_YoY":null,"영업이익률":31.2,"영업이익률_QoQ":null,"영업이익률_YoY":null,"periodEndMonth":"2019-08"},"2019-11":{"매출액_QoQ":4.3,"매출액_YoY":null,"매출총이익률":null,"매출총이익률_QoQ":null,"매출총이익률_YoY":null,"영업이익률":33.1,"영업이익률_QoQ":1.9,"영업이익률_YoY":null,"periodEndMonth":"2019-11"},"2020-02":{"매출액_QoQ":1.9,"매출액_YoY":null,"매출총이익률":null,"매출총이익률_QoQ":null,"매출총이익률_YoY":null,"영업이익률":36,"영업이익률_QoQ":2.9,"영업이익률_YoY":null,"periodEndMonth":"2020-02"},"2020-05":{"매출액_QoQ":6.6,"매출액_YoY":null,"매출총이익률":null,"매출총이익률_QoQ":null,"매출총이익률_YoY":null,"영업이익률":41.3,"영업이익률_QoQ":5.3,"영업이익률_YoY":null,"periodEndMonth":"2020-05"},"2020-08":{"매출액_QoQ":-10.3,"매출액_YoY":1.6,"매출총이익률":null,"매출총이익률_QoQ":null,"매출총이익률_YoY":null,"영업이익률":34.3,"영업이익률_QoQ":-7,"영업이익률_YoY":3.1,"periodEndMonth":"2020-08"},"2020-11":{"매출액_QoQ":4.6,"매출액_YoY":1.9,"매출총이익률":null,"매출총이익률_QoQ":null,"매출총이익률_YoY":null,"영업이익률":36.6,"영업이익률_QoQ":2.3,"영업이익률_YoY":3.5,"periodEndMonth":"2020-11"},"2021-02":{"매출액_QoQ":2.9,"매출액_YoY":2.9,"매출총이익률":null,"매출총이익률_QoQ":null,"매출총이익률_YoY":null,"영업이익률":38.5,"영업이익률_QoQ":1.9,"영업이익률_YoY":2.5,"periodEndMonth":"2021-02"},"2021-05":{"매출액_QoQ":11.3,"매출액_YoY":7.5,"매출총이익률":null,"매출총이익률_QoQ":null,"매출총이익률_YoY":null,"영업이익률":40.4,"영업이익률_QoQ":1.9,"영업이익률_YoY":-0.9,"periodEndMonth":"2021-05"},"2021-08":{"매출액_QoQ":-13.4,"매출액_YoY":3.9,"매출총이익률":null,"매출총이익률_QoQ":null,"매출총이익률_YoY":null,"영업이익률":35.2,"영업이익률_QoQ":-5.2,"영업이익률_YoY":0.9,"periodEndMonth":"2021-08"},"2021-11":{"매출액_QoQ":6.5,"매출액_YoY":5.7,"매출총이익률":null,"매출총이익률_QoQ":null,"매출총이익률_YoY":null,"영업이익률":-8,"영업이익률_QoQ":-43.2,"영업이익률_YoY":-44.6,"periodEndMonth":"2021-11"},"2022-02":{"매출액_QoQ":1.5,"매출액_YoY":4.2,"매출총이익률":null,"매출총이익률_QoQ":null,"매출총이익률_YoY":null,"영업이익률":36.4,"영업이익률_QoQ":44.4,"영업이익률_YoY":-2.1,"periodEndMonth":"2022-02"},"2022-05":{"매출액_QoQ":12.6,"매출액_YoY":5.5,"매출총이익률":null,"매출총이익률_QoQ":null,"매출총이익률_YoY":null,"영업이익률":38,"영업이익률_QoQ":1.6,"영업이익률_YoY":-2.4,"periodEndMonth":"2022-05"},"2022-08":{"매출액_QoQ":-3.3,"매출액_YoY":17.7,"매출총이익률":null,"매출총이익률_QoQ":null,"매출총이익률_YoY":null,"영업이익률":22.9,"영업이익률_QoQ":-15.1,"영업이익률_YoY":-12.3,"periodEndMonth":"2022-08"},"2022-11":{"매출액_QoQ":7.3,"매출액_YoY":18.5,"매출총이익률":null,"매출총이익률_QoQ":null,"매출총이익률_YoY":null,"영업이익률":25,"영업이익률_QoQ":2.1,"영업이익률_YoY":33,"periodEndMonth":"2022-11"},"2023-02":{"매출액_QoQ":1,"매출액_YoY":17.9,"매출총이익률":null,"매출총이익률_QoQ":null,"매출총이익률_YoY":null,"영업이익률":26.3,"영업이익률_QoQ":1.3,"영업이익률_YoY":-10.1,"periodEndMonth":"2023-02"},"2023-05":{"매출액_QoQ":11.6,"매출액_YoY":16.9,"매출총이익률":null,"매출총이익률_QoQ":null,"매출총이익률_YoY":null,"영업이익률":29.9,"영업이익률_QoQ":3.6,"영업이익률_YoY":-8.1,"periodEndMonth":"2023-05"},"2023-08":{"매출액_QoQ":-10,"매출액_YoY":8.8,"매출총이익률":71,"매출총이익률_QoQ":null,"매출총이익률_YoY":null,"영업이익률":26.5,"영업이익률_QoQ":-3.4,"영업이익률_YoY":3.6,"periodEndMonth":"2023-08"},"2023-11":{"매출액_QoQ":3.9,"매출액_YoY":5.4,"매출총이익률":71.1,"매출총이익률_QoQ":0.1,"매출총이익률_YoY":null,"영업이익률":28,"영업이익률_QoQ":1.5,"영업이익률_YoY":3,"periodEndMonth":"2023-11"},"2024-02":{"매출액_QoQ":2.6,"매출액_YoY":7.1,"매출총이익률":70.9,"매출총이익률_QoQ":-0.2,"매출총이익률_YoY":null,"영업이익률":28.2,"영업이익률_QoQ":0.2,"영업이익률_YoY":1.9,"periodEndMonth":"2024-02"},"2024-05":{"매출액_QoQ":7.6,"매출액_YoY":3.3,"매출총이익률":72.5,"매출총이익률_QoQ":1.6,"매출총이익률_YoY":null,"영업이익률":32.8,"영업이익률_QoQ":4.6,"영업이익률_YoY":2.9,"periodEndMonth":"2024-05"},"2024-08":{"매출액_QoQ":-6.9,"매출액_YoY":6.9,"매출총이익률":70.6,"매출총이익률_QoQ":-1.9,"매출총이익률_YoY":-0.4,"영업이익률":30,"영업이익률_QoQ":-2.8,"영업이익률_YoY":3.5,"periodEndMonth":"2024-08"},"2024-11":{"매출액_QoQ":5.7,"매출액_YoY":8.6,"매출총이익률":70.9,"매출총이익률_QoQ":0.3,"매출총이익률_YoY":-0.2,"영업이익률":30,"영업이익률_QoQ":0,"영업이익률_YoY":2,"periodEndMonth":"2024-11"},"2025-02":{"매출액_QoQ":0.5,"매출액_YoY":6.4,"매출총이익률":70.3,"매출총이익률_QoQ":-0.6,"매출총이익률_YoY":-0.6,"영업이익률":30.8,"영업이익률_QoQ":0.8,"영업이익률_YoY":2.6,"periodEndMonth":"2025-02"},"2025-05":{"매출액_QoQ":12.5,"매출액_YoY":11.3,"매출총이익률":70.2,"매출총이익률_QoQ":-0.1,"매출총이익률_YoY":-2.3,"영업이익률":32.1,"영업이익률_QoQ":1.3,"영업이익률_YoY":-0.7,"periodEndMonth":"2025-05"},"2025-08":{"매출액_QoQ":-6.1,"매출액_YoY":12.2,"매출총이익률":67.3,"매출총이익률_QoQ":-2.9,"매출총이익률_YoY":-3.3,"영업이익률":28.7,"영업이익률_QoQ":-3.4,"영업이익률_YoY":-1.3,"periodEndMonth":"2025-08"},"2025-11":{"매출액_QoQ":7.6,"매출액_YoY":14.2,"매출총이익률":66.5,"매출총이익률_QoQ":-0.8,"매출총이익률_YoY":-4.4,"영업이익률":56.1,"영업이익률_QoQ":27.4,"영업이익률_YoY":26.1,"periodEndMonth":"2025-11"},"2026-02":{"매출액_QoQ":7,"매출액_YoY":21.7,"매출총이익률":64.6,"매출총이익률_QoQ":-1.9,"매출총이익률_YoY":-5.7,"영업이익률":32.7,"영업이익률_QoQ":-23.4,"영업이익률_YoY":1.9,"periodEndMonth":"2026-02"}},"SIMO":{"2023-09":{"매출액_QoQ":null,"매출액_YoY":null,"매출총이익률":42.5,"매출총이익률_QoQ":null,"매출총이익률_YoY":null,"영업이익률":9.1,"영업이익률_QoQ":null,"영업이익률_YoY":null,"periodEndMonth":"2023-09"},"2023-12":{"매출액_QoQ":17.5,"매출액_YoY":null,"매출총이익률":42.1,"매출총이익률_QoQ":-0.4,"매출총이익률_YoY":null,"영업이익률":7.4,"영업이익률_QoQ":-1.7,"영업이익률_YoY":null,"periodEndMonth":"2023-12"},"2024-03":{"매출액_QoQ":-6.5,"매출액_YoY":null,"매출총이익률":45,"매출총이익률_QoQ":2.9,"매출총이익률_YoY":null,"영업이익률":9.5,"영업이익률_QoQ":2.1,"영업이익률_YoY":null,"periodEndMonth":"2024-03"},"2024-06":{"매출액_QoQ":11.3,"매출액_YoY":null,"매출총이익률":45.9,"매출총이익률_QoQ":0.9,"매출총이익률_YoY":null,"영업이익률":15.2,"영업이익률_QoQ":5.7,"영업이익률_YoY":null,"periodEndMonth":"2024-06"},"2024-09":{"매출액_QoQ":0.8,"매출액_YoY":23.3,"매출총이익률":46.8,"매출총이익률_QoQ":0.9,"매출총이익률_YoY":4.3,"영업이익률":11.5,"영업이익률_QoQ":-3.7,"영업이익률_YoY":2.4,"periodEndMonth":"2024-09"},"2024-12":{"매출액_QoQ":-10,"매출액_YoY":-5.5,"매출총이익률":45.8,"매출총이익률_QoQ":-1,"매출총이익률_YoY":3.7,"영업이익률":9.3,"영업이익률_QoQ":-2.2,"영업이익률_YoY":1.9,"periodEndMonth":"2024-12"},"2025-03":{"매출액_QoQ":-12.9,"매출액_YoY":-12,"매출총이익률":47.1,"매출총이익률_QoQ":1.3,"매출총이익률_YoY":2.1,"영업이익률":5.9,"영업이익률_QoQ":-3.4,"영업이익률_YoY":-3.6,"periodEndMonth":"2025-03"},"2025-06":{"매출액_QoQ":19.3,"매출액_YoY":-5.7,"매출총이익률":47.7,"매출총이익률_QoQ":0.6,"매출총이익률_YoY":1.8,"영업이익률":11.2,"영업이익률_QoQ":5.3,"영업이익률_YoY":-4,"periodEndMonth":"2025-06"},"2025-09":{"매출액_QoQ":21.8,"매출액_YoY":13.9,"매출총이익률":48.6,"매출총이익률_QoQ":0.9,"매출총이익률_YoY":1.8,"영업이익률":12.1,"영업이익률_QoQ":0.9,"영업이익률_YoY":0.6,"periodEndMonth":"2025-09"},"2025-12":{"매출액_QoQ":15.1,"매출액_YoY":45.7,"매출총이익률":49.1,"매출총이익률_QoQ":0.5,"매출총이익률_YoY":3.3,"영업이익률":11.4,"영업이익률_QoQ":-0.7,"영업이익률_YoY":2.1,"periodEndMonth":"2025-12"}},"SNDK":{"2023-09":{"매출액_QoQ":null,"매출액_YoY":null,"매출총이익률":-12.3,"매출총이익률_QoQ":null,"매출총이익률_YoY":null,"영업이익률":-35.6,"영업이익률_QoQ":null,"영업이익률_YoY":null,"periodEndMonth":"2023-09"},"2023-12":{"매출액_QoQ":8.6,"매출액_YoY":null,"매출총이익률":9.7,"매출총이익률_QoQ":22,"매출총이익률_YoY":null,"영업이익률":-11.9,"영업이익률_QoQ":23.7,"영업이익률_YoY":null,"periodEndMonth":"2023-12"},"2024-03":{"매출액_QoQ":2.4,"매출액_YoY":null,"매출총이익률":27.2,"매출총이익률_QoQ":17.5,"매출총이익률_YoY":null,"영업이익률":4.6,"영업이익률_QoQ":16.5,"영업이익률_YoY":null,"periodEndMonth":"2024-03"},"2024-06":{"매출액_QoQ":3.2,"매출액_YoY":null,"매출총이익률":34.1,"매출총이익률_QoQ":6.9,"매출총이익률_YoY":null,"영업이익률":10.5,"영업이익률_QoQ":5.9,"영업이익률_YoY":null,"periodEndMonth":"2024-06"},"2024-09":{"매출액_QoQ":7,"매출액_YoY":22.8,"매출총이익률":38.6,"매출총이익률_QoQ":4.5,"매출총이익률_YoY":50.9,"영업이익률":16.6,"영업이익률_QoQ":6.1,"영업이익률_YoY":52.2,"periodEndMonth":"2024-09"},"2024-12":{"매출액_QoQ":-0.4,"매출액_YoY":12.7,"매출총이익률":32.3,"매출총이익률_QoQ":-6.3,"매출총이익률_YoY":22.6,"영업이익률":9.9,"영업이익률_QoQ":-6.7,"영업이익률_YoY":21.8,"periodEndMonth":"2024-12"},"2025-03":{"매출액_QoQ":-9.6,"매출액_YoY":-0.6,"매출총이익률":22.5,"매출총이익률_QoQ":-9.8,"매출총이익률_YoY":-4.7,"영업이익률":-2.5,"영업이익률_QoQ":-12.4,"영업이익률_YoY":-7.1,"periodEndMonth":"2025-03"},"2025-06":{"매출액_QoQ":12.2,"매출액_YoY":8,"매출총이익률":26.2,"매출총이익률_QoQ":3.7,"매출총이익률_YoY":-7.9,"영업이익률":2.7,"영업이익률_QoQ":5.2,"영업이익률_YoY":-7.8,"periodEndMonth":"2025-06"},"2025-10":{"매출액_QoQ":21.4,"매출액_YoY":22.6,"매출총이익률":29.8,"매출총이익률_QoQ":3.6,"매출총이익률_YoY":-8.8,"영업이익률":8.3,"영업이익률_QoQ":5.6,"영업이익률_YoY":-8.3,"periodEndMonth":"2025-10"},"2026-01":{"매출액_QoQ":31.1,"매출액_YoY":61.2,"매출총이익률":50.9,"매출총이익률_QoQ":21.1,"매출총이익률_YoY":18.6,"영업이익률":35.5,"영업이익률_QoQ":27.2,"영업이익률_YoY":25.6,"periodEndMonth":"2026-01"}},"SSNLF":{"2016-03":{"매출액_QoQ":null,"매출액_YoY":null,"매출총이익률":39,"매출총이익률_QoQ":null,"매출총이익률_YoY":null,"영업이익률":13.4,"영업이익률_QoQ":null,"영업이익률_YoY":null,"periodEndMonth":"2016-03"},"2016-06":{"매출액_QoQ":2.3,"매출액_YoY":null,"매출총이익률":41.9,"매출총이익률_QoQ":2.9,"매출총이익률_YoY":null,"영업이익률":16,"영업이익률_QoQ":2.6,"영업이익률_YoY":null,"periodEndMonth":"2016-06"},"2016-09":{"매출액_QoQ":-6.1,"매출액_YoY":null,"매출총이익률":38.5,"매출총이익률_QoQ":-3.4,"매출총이익률_YoY":null,"영업이익률":10.9,"영업이익률_QoQ":-5.1,"영업이익률_YoY":null,"periodEndMonth":"2016-09"},"2016-12":{"매출액_QoQ":11.5,"매출액_YoY":null,"매출총이익률":42.1,"매출총이익률_QoQ":3.6,"매출총이익률_YoY":null,"영업이익률":17.3,"영업이익률_QoQ":6.4,"영업이익률_YoY":null,"periodEndMonth":"2016-12"},"2017-03":{"매출액_QoQ":-5.2,"매출액_YoY":1.5,"매출총이익률":44.3,"매출총이익률_QoQ":2.2,"매출총이익률_YoY":5.3,"영업이익률":19.6,"영업이익률_QoQ":2.3,"영업이익률_YoY":6.2,"periodEndMonth":"2017-03"},"2017-06":{"매출액_QoQ":20.7,"매출액_YoY":19.8,"매출총이익률":46.9,"매출총이익률_QoQ":2.6,"매출총이익률_YoY":5,"영업이익률":23.1,"영업이익률_QoQ":3.5,"영업이익률_YoY":7.1,"periodEndMonth":"2017-06"},"2017-09":{"매출액_QoQ":1.7,"매출액_YoY":29.8,"매출총이익률":46.8,"매출총이익률_QoQ":-0.1,"매출총이익률_YoY":8.3,"영업이익률":23.4,"영업이익률_QoQ":0.3,"영업이익률_YoY":12.5,"periodEndMonth":"2017-09"},"2017-12":{"매출액_QoQ":6.3,"매출액_YoY":23.7,"매출총이익률":45.8,"매출총이익률_QoQ":-1,"매출총이익률_YoY":3.7,"영업이익률":23,"영업이익률_QoQ":-0.4,"영업이익률_YoY":5.7,"periodEndMonth":"2017-12"},"2018-03":{"매출액_QoQ":-8.2,"매출액_YoY":19.8,"매출총이익률":47.3,"매출총이익률_QoQ":1.5,"매출총이익률_YoY":3,"영업이익률":25.8,"영업이익률_QoQ":2.8,"영업이익률_YoY":6.2,"periodEndMonth":"2018-03"},"2018-06":{"매출액_QoQ":-3.4,"매출액_YoY":-4.1,"매출총이익률":46.5,"매출총이익률_QoQ":-0.8,"매출총이익률_YoY":-0.4,"영업이익률":25.4,"영업이익률_QoQ":-0.4,"영업이익률_YoY":2.3,"periodEndMonth":"2018-06"},"2018-09":{"매출액_QoQ":11.9,"매출액_YoY":5.5,"매출총이익률":46.2,"매출총이익률_QoQ":-0.3,"매출총이익률_YoY":-0.6,"영업이익률":26.8,"영업이익률_QoQ":1.4,"영업이익률_YoY":3.4,"periodEndMonth":"2018-09"},"2018-12":{"매출액_QoQ":-9.5,"매출액_YoY":-10.2,"매출총이익률":42.6,"매출총이익률_QoQ":-3.6,"매출총이익률_YoY":-3.2,"영업이익률":18.2,"영업이익률_QoQ":-8.6,"영업이익률_YoY":-4.8,"periodEndMonth":"2018-12"},"2019-03":{"매출액_QoQ":-11.6,"매출액_YoY":-13.5,"매출총이익률":37.5,"매출총이익률_QoQ":-5.1,"매출총이익률_YoY":-9.8,"영업이익률":11.9,"영업이익률_QoQ":-6.3,"영업이익률_YoY":-13.9,"periodEndMonth":"2019-03"},"2019-06":{"매출액_QoQ":7.1,"매출액_YoY":-4,"매출총이익률":36,"매출총이익률_QoQ":-1.5,"매출총이익률_YoY":-10.5,"영업이익률":11.8,"영업이익률_QoQ":-0.1,"영업이익률_YoY":-13.6,"periodEndMonth":"2019-06"},"2019-09":{"매출액_QoQ":10.5,"매출액_YoY":-5.3,"매출총이익률":35.5,"매출총이익률_QoQ":-0.5,"매출총이익률_YoY":-10.7,"영업이익률":12.5,"영업이익률_QoQ":0.7,"영업이익률_YoY":-14.3,"periodEndMonth":"2019-09"},"2019-12":{"매출액_QoQ":-3.4,"매출액_YoY":1,"매출총이익률":35.6,"매출총이익률_QoQ":0.1,"매출총이익률_YoY":-7,"영업이익률":12,"영업이익률_QoQ":-0.5,"영업이익률_YoY":-6.2,"periodEndMonth":"2019-12"},"2020-03":{"매출액_QoQ":-7.6,"매출액_YoY":5.6,"매출총이익률":37.1,"매출총이익률_QoQ":1.5,"매출총이익률_YoY":-0.4,"영업이익률":11.7,"영업이익률_QoQ":-0.3,"영업이익률_YoY":-0.2,"periodEndMonth":"2020-03"},"2020-06":{"매출액_QoQ":-4.3,"매출액_YoY":-5.6,"매출총이익률":39.8,"매출총이익률_QoQ":2.7,"매출총이익률_YoY":3.8,"영업이익률":15.4,"영업이익률_QoQ":3.7,"영업이익률_YoY":3.6,"periodEndMonth":"2020-06"},"2020-09":{"매출액_QoQ":26.4,"매출액_YoY":8,"매출총이익률":40.3,"매출총이익률_QoQ":0.5,"매출총이익률_YoY":4.8,"영업이익률":18.4,"영업이익률_QoQ":3,"영업이익률_YoY":5.9,"periodEndMonth":"2020-09"},"2020-12":{"매출액_QoQ":-8.1,"매출액_YoY":2.8,"매출총이익률":38.6,"매출총이익률_QoQ":-1.7,"매출총이익률_YoY":3,"영업이익률":14.7,"영업이익률_QoQ":-3.7,"영업이익률_YoY":2.7,"periodEndMonth":"2020-12"},"2021-03":{"매출액_QoQ":6.2,"매출액_YoY":18.2,"매출총이익률":36.5,"매출총이익률_QoQ":-2.1,"매출총이익률_YoY":-0.6,"영업이익률":14.3,"영업이익률_QoQ":-0.4,"영업이익률_YoY":2.6,"periodEndMonth":"2021-03"},"2021-06":{"매출액_QoQ":-2.6,"매출액_YoY":20.2,"매출총이익률":41.8,"매출총이익률_QoQ":5.3,"매출총이익률_YoY":2,"영업이익률":19.7,"영업이익률_QoQ":5.4,"영업이익률_YoY":4.3,"periodEndMonth":"2021-06"},"2021-09":{"매출액_QoQ":16.2,"매출액_YoY":10.5,"매출총이익률":42,"매출총이익률_QoQ":0.2,"매출총이익률_YoY":1.7,"영업이익률":21.4,"영업이익률_QoQ":1.7,"영업이익률_YoY":3,"periodEndMonth":"2021-09"},"2021-12":{"매출액_QoQ":3.5,"매출액_YoY":24.4,"매출총이익률":41.3,"매출총이익률_QoQ":-0.7,"매출총이익률_YoY":2.7,"영업이익률":18.1,"영업이익률_QoQ":-3.3,"영업이익률_YoY":3.4,"periodEndMonth":"2021-12"},"2022-03":{"매출액_QoQ":1.6,"매출액_YoY":19,"매출총이익률":39.5,"매출총이익률_QoQ":-1.8,"매출총이익률_YoY":3,"영업이익률":18.2,"영업이익률_QoQ":0.1,"영업이익률_YoY":3.9,"periodEndMonth":"2022-03"},"2022-06":{"매출액_QoQ":-0.7,"매출액_YoY":21.3,"매출총이익률":40.1,"매출총이익률_QoQ":0.6,"매출총이익률_YoY":-1.7,"영업이익률":18.3,"영업이익률_QoQ":0.1,"영업이익률_YoY":-1.4,"periodEndMonth":"2022-06"},"2022-09":{"매출액_QoQ":-0.5,"매출액_YoY":3.8,"매출총이익률":37.4,"매출총이익률_QoQ":-2.7,"매출총이익률_YoY":-4.6,"영업이익률":14.1,"영업이익률_QoQ":-4.2,"영업이익률_YoY":-7.3,"periodEndMonth":"2022-09"},"2022-12":{"매출액_QoQ":-8.2,"매출액_YoY":-8,"매출총이익률":31,"매출총이익률_QoQ":-6.4,"매출총이익률_YoY":-10.3,"영업이익률":6.1,"영업이익률_QoQ":-8,"영업이익률_YoY":-12,"periodEndMonth":"2022-12"},"2023-03":{"매출액_QoQ":-9.5,"매출액_YoY":-18,"매출총이익률":27.8,"매출총이익률_QoQ":-3.2,"매출총이익률_YoY":-11.7,"영업이익률":1,"영업이익률_QoQ":-5.1,"영업이익률_YoY":-17.2,"periodEndMonth":"2023-03"},"2023-06":{"매출액_QoQ":-5.9,"매출액_YoY":-22.3,"매출총이익률":30.6,"매출총이익률_QoQ":2.8,"매출총이익률_YoY":-9.5,"영업이익률":1.1,"영업이익률_QoQ":0.1,"영업이익률_YoY":-17.2,"periodEndMonth":"2023-06"},"2023-09":{"매출액_QoQ":12.3,"매출액_YoY":-12.2,"매출총이익률":30.8,"매출총이익률_QoQ":0.2,"매출총이익률_YoY":-6.6,"영업이익률":3.6,"영업이익률_QoQ":2.5,"영업이익률_YoY":-10.5,"periodEndMonth":"2023-09"},"2023-12":{"매출액_QoQ":0.6,"매출액_YoY":-3.8,"매출총이익률":32,"매출총이익률_QoQ":1.2,"매출총이익률_YoY":1,"영업이익률":4.2,"영업이익률_QoQ":0.6,"영업이익률_YoY":-1.9,"periodEndMonth":"2023-12"},"2024-03":{"매출액_QoQ":6.1,"매출액_YoY":12.8,"매출총이익률":36.2,"매출총이익률_QoQ":4.2,"매출총이익률_YoY":8.4,"영업이익률":9.2,"영업이익률_QoQ":5,"영업이익률_YoY":8.2,"periodEndMonth":"2024-03"},"2024-06":{"매출액_QoQ":3,"매출액_YoY":23.4,"매출총이익률":40.2,"매출총이익률_QoQ":4,"매출총이익률_YoY":9.6,"영업이익률":14.1,"영업이익률_QoQ":4.9,"영업이익률_YoY":13,"periodEndMonth":"2024-06"},"2024-09":{"매출액_QoQ":6.8,"매출액_YoY":17.3,"매출총이익률":37.9,"매출총이익률_QoQ":-2.3,"매출총이익률_YoY":7.1,"영업이익률":11.6,"영업이익률_QoQ":-2.5,"영업이익률_YoY":8,"periodEndMonth":"2024-09"},"2024-12":{"매출액_QoQ":-4.2,"매출액_YoY":11.8,"매출총이익률":37.6,"매출총이익률_QoQ":-0.3,"매출총이익률_YoY":5.6,"영업이익률":8.6,"영업이익률_QoQ":-3,"영업이익률_YoY":4.4,"periodEndMonth":"2024-12"},"2025-03":{"매출액_QoQ":4.4,"매출액_YoY":10,"매출총이익률":35.5,"매출총이익률_QoQ":-2.1,"매출총이익률_YoY":-0.7,"영업이익률":8.4,"영업이익률_QoQ":-0.2,"영업이익률_YoY":-0.8,"periodEndMonth":"2025-03"},"2025-06":{"매출액_QoQ":-5.8,"매출액_YoY":0.7,"매출총이익률":34.2,"매출총이익률_QoQ":-1.3,"매출총이익률_YoY":-6,"영업이익률":6.3,"영업이익률_QoQ":-2.1,"영업이익률_YoY":-7.8,"periodEndMonth":"2025-06"},"2025-09":{"매출액_QoQ":15.4,"매출액_YoY":8.8,"매출총이익률":38.9,"매출총이익률_QoQ":4.7,"매출총이익률_YoY":1,"영업이익률":14.1,"영업이익률_QoQ":7.8,"영업이익률_YoY":2.5,"periodEndMonth":"2025-09"},"2025-12":{"매출액_QoQ":9,"매출액_YoY":23.8,"매출총이익률":47.2,"매출총이익률_QoQ":8.3,"매출총이익률_YoY":9.6,"영업이익률":21.4,"영업이익률_QoQ":7.3,"영업이익률_YoY":12.8,"periodEndMonth":"2025-12"}},"STX":{"2021-04":{"매출액_QoQ":null,"매출액_YoY":null,"매출총이익률":null,"매출총이익률_QoQ":null,"매출총이익률_YoY":null,"영업이익률":14.1,"영업이익률_QoQ":null,"영업이익률_YoY":null,"periodEndMonth":"2021-04"},"2021-07":{"매출액_QoQ":10.3,"매출액_YoY":null,"매출총이익률":null,"매출총이익률_QoQ":null,"매출총이익률_YoY":null,"영업이익률":16.8,"영업이익률_QoQ":2.7,"영업이익률_YoY":null,"periodEndMonth":"2021-07"},"2021-10":{"매출액_QoQ":3.4,"매출액_YoY":null,"매출총이익률":null,"매출총이익률_QoQ":null,"매출총이익률_YoY":null,"영업이익률":18.8,"영업이익률_QoQ":2,"영업이익률_YoY":null,"periodEndMonth":"2021-10"},"2021-12":{"매출액_QoQ":0,"매출액_YoY":null,"매출총이익률":null,"매출총이익률_QoQ":null,"매출총이익률_YoY":null,"영업이익률":18.6,"영업이익률_QoQ":-0.2,"영업이익률_YoY":null,"periodEndMonth":"2021-12"},"2022-04":{"매출액_QoQ":-10.1,"매출액_YoY":2.6,"매출총이익률":null,"매출총이익률_QoQ":null,"매출총이익률_YoY":null,"영업이익률":15.3,"영업이익률_QoQ":-3.3,"영업이익률_YoY":1.2,"periodEndMonth":"2022-04"},"2022-07":{"매출액_QoQ":-6.2,"매출액_YoY":-12.8,"매출총이익률":null,"매출총이익률_QoQ":null,"매출총이익률_YoY":null,"영업이익률":13.7,"영업이익률_QoQ":-1.6,"영업이익률_YoY":-3.1,"periodEndMonth":"2022-07"},"2022-09":{"매출액_QoQ":-22.6,"매출액_YoY":-34.7,"매출총이익률":null,"매출총이익률_QoQ":null,"매출총이익률_YoY":null,"영업이익률":5.3,"영업이익률_QoQ":-8.4,"영업이익률_YoY":-13.5,"periodEndMonth":"2022-09"},"2022-12":{"매출액_QoQ":-7.3,"매출액_YoY":-39.4,"매출총이익률":null,"매출총이익률_QoQ":null,"매출총이익률_YoY":null,"영업이익률":-8.5,"영업이익률_QoQ":-13.8,"영업이익률_YoY":-27.1,"periodEndMonth":"2022-12"},"2023-03":{"매출액_QoQ":-1.4,"매출액_YoY":-33.6,"매출총이익률":null,"매출총이익률_QoQ":null,"매출총이익률_YoY":null,"영업이익률":-16.9,"영업이익률_QoQ":-8.4,"영업이익률_YoY":-32.2,"periodEndMonth":"2023-03"},"2023-06":{"매출액_QoQ":-13.9,"매출액_YoY":-39,"매출총이익률":23.2,"매출총이익률_QoQ":null,"매출총이익률_YoY":null,"영업이익률":1.6,"영업이익률_QoQ":18.5,"영업이익률_YoY":-12.1,"periodEndMonth":"2023-06"},"2023-09":{"매출액_QoQ":-9.2,"매출액_YoY":-28.6,"매출총이익률":11.1,"매출총이익률_QoQ":-12.1,"매출총이익률_YoY":null,"영업이익률":-8.9,"영업이익률_QoQ":-10.5,"영업이익률_YoY":-14.2,"periodEndMonth":"2023-09"},"2023-12":{"매출액_QoQ":6.9,"매출액_YoY":-17.6,"매출총이익률":23.3,"매출총이익률_QoQ":12.2,"매출총이익률_YoY":null,"영업이익률":8,"영업이익률_QoQ":16.9,"영업이익률_YoY":16.5,"periodEndMonth":"2023-12"},"2024-03":{"매출액_QoQ":6.4,"매출액_YoY":-11,"매출총이익률":25.7,"매출총이익률_QoQ":2.4,"매출총이익률_YoY":null,"영업이익률":8.6,"영업이익률_QoQ":0.6,"영업이익률_YoY":25.5,"periodEndMonth":"2024-03"},"2024-06":{"매출액_QoQ":14,"매출액_YoY":17.8,"매출총이익률":31.8,"매출총이익률_QoQ":6.1,"매출총이익률_YoY":8.6,"영업이익률":16.6,"영업이익률_QoQ":8,"영업이익률_YoY":15,"periodEndMonth":"2024-06"},"2024-09":{"매출액_QoQ":14.9,"매출액_YoY":49.1,"매출총이익률":32.9,"매출총이익률_QoQ":1.1,"매출총이익률_YoY":21.8,"영업이익률":18.6,"영업이익률_QoQ":2,"영업이익률_YoY":27.5,"periodEndMonth":"2024-09"},"2024-12":{"매출액_QoQ":7.2,"매출액_YoY":49.5,"매출총이익률":34.9,"매출총이익률_QoQ":2,"매출총이익률_YoY":11.6,"영업이익률":21,"영업이익률_QoQ":2.4,"영업이익률_YoY":13,"periodEndMonth":"2024-12"},"2025-03":{"매출액_QoQ":-7.1,"매출액_YoY":30.5,"매출총이익률":35.6,"매출총이익률_QoQ":0.7,"매출총이익률_YoY":9.9,"영업이익률":20,"영업이익률_QoQ":-1,"영업이익률_YoY":11.4,"periodEndMonth":"2025-03"},"2025-06":{"매출액_QoQ":13.1,"매출액_YoY":29.5,"매출총이익률":37.5,"매출총이익률_QoQ":1.9,"매출총이익률_YoY":5.7,"영업이익률":23.9,"영업이익률_QoQ":3.9,"영업이익률_YoY":7.3,"periodEndMonth":"2025-06"},"2025-10":{"매출액_QoQ":7.6,"매출액_YoY":21.3,"매출총이익률":39.4,"매출총이익률_QoQ":1.9,"매출총이익률_YoY":6.5,"영업이익률":26.9,"영업이익률_QoQ":3,"영업이익률_YoY":8.3,"periodEndMonth":"2025-10"},"2026-01":{"매출액_QoQ":7.5,"매출액_YoY":21.5,"매출총이익률":41.6,"매출총이익률_QoQ":2.2,"매출총이익률_YoY":6.7,"영업이익률":29.9,"영업이익률_QoQ":3,"영업이익률_YoY":8.9,"periodEndMonth":"2026-01"}},"WDC":{"2021-04":{"매출액_QoQ":null,"매출액_YoY":null,"매출총이익률":26.4,"매출총이익률_QoQ":null,"매출총이익률_YoY":null,"영업이익률":7.7,"영업이익률_QoQ":null,"영업이익률_YoY":null,"periodEndMonth":"2021-04"},"2021-07":{"매출액_QoQ":18.9,"매출액_YoY":null,"매출총이익률":31.8,"매출총이익률_QoQ":5.4,"매출총이익률_YoY":null,"영업이익률":13.7,"영업이익률_QoQ":6,"영업이익률_YoY":null,"periodEndMonth":"2021-07"},"2021-10":{"매출액_QoQ":2.7,"매출액_YoY":null,"매출총이익률":33,"매출총이익률_QoQ":1.2,"매출총이익률_YoY":null,"영업이익률":15.4,"영업이익률_QoQ":1.7,"영업이익률_YoY":null,"periodEndMonth":"2021-10"},"2021-12":{"매출액_QoQ":-4.3,"매출액_YoY":null,"매출총이익률":32.8,"매출총이익률_QoQ":-0.2,"매출총이익률_YoY":null,"영업이익률":15,"영업이익률_QoQ":-0.4,"영업이익률_YoY":null,"periodEndMonth":"2021-12"},"2022-04":{"매출액_QoQ":-9.4,"매출액_YoY":5.9,"매출총이익률":27,"매출총이익률_QoQ":-5.8,"매출총이익률_YoY":0.6,"영업이익률":7.4,"영업이익률_QoQ":-7.6,"영업이익률_YoY":-0.3,"periodEndMonth":"2022-04"},"2022-07":{"매출액_QoQ":3.4,"매출액_YoY":-8,"매출총이익률":31.9,"매출총이익률_QoQ":4.9,"매출총이익률_YoY":0.1,"영업이익률":12.4,"영업이익률_QoQ":5,"영업이익률_YoY":-1.3,"periodEndMonth":"2022-07"},"2022-09":{"매출액_QoQ":-17.5,"매출액_YoY":-26,"매출총이익률":26.3,"매출총이익률_QoQ":-5.6,"매출총이익률_YoY":-6.7,"영업이익률":4.2,"영업이익률_QoQ":-8.2,"영업이익률_YoY":-11.2,"periodEndMonth":"2022-09"},"2022-12":{"매출액_QoQ":-16.8,"매출액_YoY":-35.7,"매출총이익률":17,"매출총이익률_QoQ":-9.3,"매출총이익률_YoY":-15.8,"영업이익률":-10.3,"영업이익률_QoQ":-14.5,"영업이익률_YoY":-25.3,"periodEndMonth":"2022-12"},"2023-03":{"매출액_QoQ":-9.8,"매출액_YoY":-36,"매출총이익률":10.2,"매출총이익률_QoQ":-6.8,"매출총이익률_YoY":-16.8,"영업이익률":-16.8,"영업이익률_QoQ":-6.5,"영업이익률_YoY":-24.2,"periodEndMonth":"2023-03"},"2023-06":{"매출액_QoQ":-4.7,"매출액_YoY":-41,"매출총이익률":3.4,"매출총이익률_QoQ":-6.8,"매출총이익률_YoY":-28.5,"영업이익률":-24.3,"영업이익률_QoQ":-7.5,"영업이익률_YoY":-36.7,"periodEndMonth":"2023-06"},"2023-09":{"매출액_QoQ":2.9,"매출액_YoY":-26.4,"매출총이익률":3.6,"매출총이익률_QoQ":0.2,"매출총이익률_YoY":-22.7,"영업이익률":-21.7,"영업이익률_QoQ":2.6,"영업이익률_YoY":-25.9,"periodEndMonth":"2023-09"},"2023-12":{"매출액_QoQ":10.3,"매출액_YoY":-2.4,"매출총이익률":16.2,"매출총이익률_QoQ":12.6,"매출총이익률_YoY":-0.8,"영업이익률":-6.9,"영업이익률_QoQ":14.8,"영업이익률_YoY":3.4,"periodEndMonth":"2023-12"},"2024-03":{"매출액_QoQ":14,"매출액_YoY":23.3,"매출총이익률":29,"매출총이익률_QoQ":12.8,"매출총이익률_YoY":18.8,"영업이익률":7.9,"영업이익률_QoQ":14.8,"영업이익률_YoY":24.7,"periodEndMonth":"2024-03"},"2024-06":{"매출액_QoQ":8.9,"매출액_YoY":40.9,"매출총이익률":35.9,"매출총이익률_QoQ":6.9,"매출총이익률_YoY":32.5,"영업이익률":5.7,"영업이익률_QoQ":-2.2,"영업이익률_YoY":30,"periodEndMonth":"2024-06"},"2024-09":{"매출액_QoQ":8.8,"매출액_YoY":48.9,"매출총이익률":37.9,"매출총이익률_QoQ":2,"매출총이익률_YoY":34.3,"영업이익률":18.1,"영업이익률_QoQ":12.4,"영업이익률_YoY":39.8,"periodEndMonth":"2024-09"},"2024-12":{"매출액_QoQ":4.6,"매출액_YoY":41.3,"매출총이익률":35.4,"매출총이익률_QoQ":-2.5,"매출총이익률_YoY":19.2,"영업이익률":19.9,"영업이익률_QoQ":1.8,"영업이익률_YoY":26.8,"periodEndMonth":"2024-12"},"2025-03":{"매출액_QoQ":-134.2,"매출액_YoY":-142.4,"매출총이익률":30.2,"매출총이익률_QoQ":-5.2,"매출총이익률_YoY":1.2,"영업이익률":-4.1,"영업이익률_QoQ":-24,"영업이익률_YoY":-12,"periodEndMonth":"2025-03"},"2025-06":{"매출액_QoQ":277.8,"매출액_YoY":-30.8,"매출총이익률":41,"매출총이익률_QoQ":10.8,"매출총이익률_YoY":5.1,"영업이익률":26.1,"영업이익률_QoQ":30.2,"영업이익률_YoY":20.4,"periodEndMonth":"2025-06"},"2025-10":{"매출액_QoQ":8.2,"매출액_YoY":-31.2,"매출총이익률":43.5,"매출총이익률_QoQ":2.5,"매출총이익률_YoY":5.6,"영업이익률":28.1,"영업이익률_QoQ":2,"영업이익률_YoY":10,"periodEndMonth":"2025-10"},"2026-01":{"매출액_QoQ":107.1,"매출액_YoY":36.2,"매출총이익률":44.7,"매출총이익률_QoQ":1.2,"매출총이익률_YoY":9.3,"영업이익률":29.1,"영업이익률_QoQ":1,"영업이익률_YoY":9.2,"periodEndMonth":"2026-01"}}}